{
  "application_number": 985,
  "address": "f2onxvf2zmed2gctynicq5zg2mdd4ilucmzmovjsa",
  "name": "Space Lab",
  "allocator_id": "f03617939",
  "organization": "Space Lab",
  "metapathway_type": "MDMA",
  "ma_address": "f410fw325e6novwl57jcsbhz6koljylxuhqq5jnp5ftq",
  "pathway_addresses": {
    "msig": "f2onxvf2zmed2gctynicq5zg2mdd4ilucmzmovjsa",
    "signers": [
      "f1lka5rj3byve5g5b7disv3weboflyg7gyk42ccya"
    ]
  },
  "associated_org_addresses": "f1lka5rj3byve5g5b7disv3weboflyg7gyk42ccya",
  "application": {
    "audit": [
      "Public Open "
    ],
    "distribution": [],
    "tranche_schedule": "I will use the standard Allocation Tranche Schedule",
    "required_sps": "over 5",
    "required_replicas": "8",
    "tooling": [
      "smart_contract_allocator"
    ],
    "github_handles": [
      "york0320"
    ],
    "allocation_bookkeeping": "https://github.com/york0320/Space-Lab",
    "client_contract_address": "f410fu6luqparfgebtrnfjibz5udm2w5nat3cwed24qa"
  },
  "history": {
    "Application Submitted": "2025-06-30T03:38:55.000Z",
    "KYC Submitted": "2025-07-01T13:15:02.000Z",
    "Approved": "2025-07-29T03:59:03.000Z",
    "Declined": "",
    "DC Allocated": "2025-07-29T06:22:37.000Z"
  },
  "audits": [
    {
      "started": "2025-06-30T03:38:47.000Z",
      "ended": "2025-07-29T03:59:03.000Z",
      "dc_allocated": "2025-07-29T06:22:37.000Z",
      "outcome": "GRANTED",
      "datacap_amount": 5
    }
  ],
  "old_allocator_id": ""
}