[
  {
    "id": 69874119,
    "clientId": 2661434,
    "providerId": 3079766,
    "pieceCid": {
      "/": "baga6ea4seaqc4lwnksu627kfyyzwliv6yckozzxenx75pzy2ldmhprfnc6kukiq"
    },
    "pieceSize": 34359738368,
    "termMin": 520000,
    "termMax": 779200,
    "expiration": 4141341,
    "height": 4126942
  },
  {
    "id": 69874118,
    "clientId": 2661434,
    "providerId": 3079766,
    "pieceCid": {
      "/": "baga6ea4seaqbolt74pcqn6sddoks7hdmsbjcdioszpxjarocb2gofz6zjpvvogy"
    },
    "pieceSize": 34359738368,
    "termMin": 520000,
    "termMax": 779200,
    "expiration": 4141341,
    "height": 4126942
  },
  {
    "id": 69874117,
    "clientId": 2661434,
    "providerId": 3079766,
    "pieceCid": {
      "/": "baga6ea4seaqd7hgamn6xoereorueitevbbqyphfknqpokevynudtk42gkrl6cdq"
    },
    "pieceSize": 34359738368,
    "termMin": 520000,
    "termMax": 779200,
    "expiration": 4141341,
    "height": 4126942
  },
  {
    "id": 69874116,
    "clientId": 2661434,
    "providerId": 3079766,
    "pieceCid": {
      "/": "baga6ea4seaqhzwclngfoeki66u4vvfjbxdb5htthxrestskag5hiycvmt4z3kiy"
    },
    "pieceSize": 34359738368,
    "termMin": 520000,
    "termMax": 779200,
    "expiration": 4141341,
    "height": 4126942
  },
  {
    "id": 69874115,
    "clientId": 2661434,
    "providerId": 3079766,
    "pieceCid": {
      "/": "baga6ea4seaqjj56ofzz77k7puogp5f7e2xv3sbtavc5eelj7fpqnpai7jwklwoi"
    },
    "pieceSize": 34359738368,
    "termMin": 520000,
    "termMax": 779200,
    "expiration": 4141340,
    "height": 4126942
  },
  {
    "id": 69874114,
    "clientId": 2661434,
    "providerId": 3079766,
    "pieceCid": {
      "/": "baga6ea4seaqisnrk23uqenbesucbfku54tekfecabfczbbef7cxfa5avc3ahudq"
    },
    "pieceSize": 34359738368,
    "termMin": 520000,
    "termMax": 779200,
    "expiration": 4141340,
    "height": 4126942
  },
  {
    "id": 69874113,
    "clientId": 2661434,
    "providerId": 3079766,
    "pieceCid": {
      "/": "baga6ea4seaqkbepfvjpgnzmcq5xqla5etsaov7gxdwjuq7htbv2rkircrsqwwjq"
    },
    "pieceSize": 34359738368,
    "termMin": 520000,
    "termMax": 779200,
    "expiration": 4141340,
    "height": 4126942
  },
  {
    "id": 69874112,
    "clientId": 2661434,
    "providerId": 3079766,
    "pieceCid": {
      "/": "baga6ea4seaqa3cyfcvc724mqvppxmsr5saqayoru6gpcjbmdmgwanrobtyngupy"
    },
    "pieceSize": 34359738368,
    "termMin": 520000,
    "termMax": 779200,
    "expiration": 4141340,
    "height": 4126942
  },
  {
    "id": 69874243,
    "clientId": 2661434,
    "providerId": 3079766,
    "pieceCid": {
      "/": "baga6ea4seaqkirj7ewesyhizwamfqxfbxaq2ns6saoxwapbaum3hbktqvvjt4by"
    },
    "pieceSize": 34359738368,
    "termMin": 520000,
    "termMax": 779200,
    "expiration": 4141327,
    "height": 4126946
  },
  {
    "id": 69874242,
    "clientId": 2661434,
    "providerId": 3079766,
    "pieceCid": {
      "/": "baga6ea4seaqamef3clskfwg2pj3rkzeqqsmyakspam36x2fxhnn4dopfqboceey"
    },
    "pieceSize": 34359738368,
    "termMin": 520000,
    "termMax": 779200,
    "expiration": 4141326,
    "height": 4126946
  },
  {
    "id": 69874241,
    "clientId": 2661434,
    "providerId": 3079766,
    "pieceCid": {
      "/": "baga6ea4seaqgdvs6zvpjqx6stnrrqbto35psxxozk5rxp46xyoi7qatu3im7gjy"
    },
    "pieceSize": 34359738368,
    "termMin": 520000,
    "termMax": 779200,
    "expiration": 4141326,
    "height": 4126946
  },
  {
    "id": 69874240,
    "clientId": 2661434,
    "providerId": 3079766,
    "pieceCid": {
      "/": "baga6ea4seaqoth7ennitj4kvsq5cgyocwhsgth6wc4plg6j4o3fhaa4vdwukaha"
    },
    "pieceSize": 34359738368,
    "termMin": 520000,
    "termMax": 779200,
    "expiration": 4141326,
    "height": 4126946
  },
  {
    "id": 69874239,
    "clientId": 2661434,
    "providerId": 3079766,
    "pieceCid": {
      "/": "baga6ea4seaqhillqkoufro5u5uzlaervyfj3dk7s3cbteulr2okiotsml7m4qla"
    },
    "pieceSize": 34359738368,
    "termMin": 520000,
    "termMax": 779200,
    "expiration": 4141326,
    "height": 4126946
  },
  {
    "id": 69874672,
    "clientId": 2661434,
    "providerId": 3079766,
    "pieceCid": {
      "/": "baga6ea4seaqbaunhwyrd6nhis44vsdufpo6fhx3ah5ahbgo7kq55myhzwufp4ly"
    },
    "pieceSize": 34359738368,
    "termMin": 520000,
    "termMax": 779200,
    "expiration": 4141341,
    "height": 4126957
  },
  {
    "id": 69874671,
    "clientId": 2661434,
    "providerId": 3079766,
    "pieceCid": {
      "/": "baga6ea4seaql7a25qzukvxyswag32bvychznanaf5kgge64jepwz5ehiav4oaoy"
    },
    "pieceSize": 34359738368,
    "termMin": 520000,
    "termMax": 779200,
    "expiration": 4141342,
    "height": 4126957
  },
  {
    "id": 69874670,
    "clientId": 2661434,
    "providerId": 3079766,
    "pieceCid": {
      "/": "baga6ea4seaqlyhnwjhwh4sd5gwhczekbsfuampkahmvdwp2vvynngsblakehkla"
    },
    "pieceSize": 34359738368,
    "termMin": 520000,
    "termMax": 779200,
    "expiration": 4141343,
    "height": 4126957
  },
  {
    "id": 69874669,
    "clientId": 2661434,
    "providerId": 3079766,
    "pieceCid": {
      "/": "baga6ea4seaqaxrvd62ue4jdvt6w2ithbm5aswmnzqeaa4oevsgjwdvbldrwuubi"
    },
    "pieceSize": 34359738368,
    "termMin": 520000,
    "termMax": 779200,
    "expiration": 4141342,
    "height": 4126957
  },
  {
    "id": 69874668,
    "clientId": 2661434,
    "providerId": 3079766,
    "pieceCid": {
      "/": "baga6ea4seaqjd5pzrimj6myf6mpwbpewwizbgv23x4ei27cevqn6cbmn7gxnwiy"
    },
    "pieceSize": 34359738368,
    "termMin": 520000,
    "termMax": 779200,
    "expiration": 4141342,
    "height": 4126957
  },
  {
    "id": 69874667,
    "clientId": 2661434,
    "providerId": 3079766,
    "pieceCid": {
      "/": "baga6ea4seaqbmtgvshzlpcgnizdalr4obyw2ponzjwemhprixlzoizjd2focwpq"
    },
    "pieceSize": 34359738368,
    "termMin": 520000,
    "termMax": 779200,
    "expiration": 4141342,
    "height": 4126957
  },
  {
    "id": 69874666,
    "clientId": 2661434,
    "providerId": 3079766,
    "pieceCid": {
      "/": "baga6ea4seaqpgx6nay3e3xc3ef6wd7zve7lxwnohxttklktvq24e4n3nhr52mpi"
    },
    "pieceSize": 34359738368,
    "termMin": 520000,
    "termMax": 779200,
    "expiration": 4141343,
    "height": 4126957
  },
  {
    "id": 69874665,
    "clientId": 2661434,
    "providerId": 3079766,
    "pieceCid": {
      "/": "baga6ea4seaqp6bu2ggquodqehd7czij3zar4lowboukhtcmelugpiu3lwoczkpq"
    },
    "pieceSize": 34359738368,
    "termMin": 520000,
    "termMax": 779200,
    "expiration": 4141342,
    "height": 4126957
  },
  {
    "id": 69874984,
    "clientId": 2661434,
    "providerId": 3079766,
    "pieceCid": {
      "/": "baga6ea4seaqe66ku2rdrebda53gddf6o2a754hlxedxirdeqo3kzjm3flu3ycca"
    },
    "pieceSize": 34359738368,
    "termMin": 520000,
    "termMax": 779200,
    "expiration": 4141356,
    "height": 4126964
  },
  {
    "id": 69874983,
    "clientId": 2661434,
    "providerId": 3079766,
    "pieceCid": {
      "/": "baga6ea4seaqnynlkvfhnyzoh6uod4mto5smbtczaqkc6ngma6rfurmwnhfhkaea"
    },
    "pieceSize": 34359738368,
    "termMin": 520000,
    "termMax": 779200,
    "expiration": 4141357,
    "height": 4126964
  },
  {
    "id": 69874982,
    "clientId": 2661434,
    "providerId": 3079766,
    "pieceCid": {
      "/": "baga6ea4seaqovauoxq3u6pqdusbmbkeyl67rd4wznqv67fcs6j2ebwcgbnbooaa"
    },
    "pieceSize": 34359738368,
    "termMin": 520000,
    "termMax": 779200,
    "expiration": 4141357,
    "height": 4126964
  },
  {
    "id": 69874981,
    "clientId": 2661434,
    "providerId": 3079766,
    "pieceCid": {
      "/": "baga6ea4seaqltix3pces34q62iy3ldpi3rmp3ntyptmzjzs44t4tquviu57ekly"
    },
    "pieceSize": 34359738368,
    "termMin": 520000,
    "termMax": 779200,
    "expiration": 4141356,
    "height": 4126964
  },
  {
    "id": 69874980,
    "clientId": 2661434,
    "providerId": 3079766,
    "pieceCid": {
      "/": "baga6ea4seaqicb6qcts35tt65rqesw45j4slkesvvkyhubyioumzbfol6szsmiy"
    },
    "pieceSize": 34359738368,
    "termMin": 520000,
    "termMax": 779200,
    "expiration": 4141358,
    "height": 4126964
  },
  {
    "id": 69874979,
    "clientId": 2661434,
    "providerId": 3079766,
    "pieceCid": {
      "/": "baga6ea4seaqaqaxq67un7fao3axeskuzm2xoc3m2ce7izlldad4syjfh6zma4pa"
    },
    "pieceSize": 34359738368,
    "termMin": 520000,
    "termMax": 779200,
    "expiration": 4141357,
    "height": 4126964
  },
  {
    "id": 69874978,
    "clientId": 2661434,
    "providerId": 3079766,
    "pieceCid": {
      "/": "baga6ea4seaqkz242uf3knksofxasodt6kcga4pt3mtoreyznim66fxppnq7zyfq"
    },
    "pieceSize": 34359738368,
    "termMin": 520000,
    "termMax": 779200,
    "expiration": 4141357,
    "height": 4126964
  },
  {
    "id": 69874977,
    "clientId": 2661434,
    "providerId": 3079766,
    "pieceCid": {
      "/": "baga6ea4seaqnqechvcircehkdx5gs66cit25d4nkk4nl7avtbxns24bja5n3ioq"
    },
    "pieceSize": 34359738368,
    "termMin": 520000,
    "termMax": 779200,
    "expiration": 4141357,
    "height": 4126964
  },
  {
    "id": 69875257,
    "clientId": 2661434,
    "providerId": 3079766,
    "pieceCid": {
      "/": "baga6ea4seaqelcxygzhvxorq7f74hplq4juvbjqflvx44k2xijkgx5oah37kyma"
    },
    "pieceSize": 34359738368,
    "termMin": 520000,
    "termMax": 779200,
    "expiration": 4141368,
    "height": 4126971
  },
  {
    "id": 69875256,
    "clientId": 2661434,
    "providerId": 3079766,
    "pieceCid": {
      "/": "baga6ea4seaqgvnvmnq5stgjm3cfpt2ggjqtimyfy56nsutqdcpkw5xxoyjzg4aq"
    },
    "pieceSize": 34359738368,
    "termMin": 520000,
    "termMax": 779200,
    "expiration": 4141369,
    "height": 4126971
  },
  {
    "id": 69875255,
    "clientId": 2661434,
    "providerId": 3079766,
    "pieceCid": {
      "/": "baga6ea4seaqp7rnwcnt5eg2rkkfz4yaels2uate47ifs5awjzqy6u3od4j7n6ki"
    },
    "pieceSize": 34359738368,
    "termMin": 520000,
    "termMax": 779200,
    "expiration": 4141369,
    "height": 4126971
  },
  {
    "id": 69875254,
    "clientId": 2661434,
    "providerId": 3079766,
    "pieceCid": {
      "/": "baga6ea4seaqipvedgbjfjv4mxtgx6vfzkbx2enbegmefs3rhp5tlznfss7aycla"
    },
    "pieceSize": 34359738368,
    "termMin": 520000,
    "termMax": 779200,
    "expiration": 4141369,
    "height": 4126971
  },
  {
    "id": 69875253,
    "clientId": 2661434,
    "providerId": 3079766,
    "pieceCid": {
      "/": "baga6ea4seaqfjo4jwiudpvds6i4ft6h7ge3rjfokzworxjsy7rpvqeb43et5kba"
    },
    "pieceSize": 34359738368,
    "termMin": 520000,
    "termMax": 779200,
    "expiration": 4141369,
    "height": 4126971
  },
  {
    "id": 69875252,
    "clientId": 2661434,
    "providerId": 3079766,
    "pieceCid": {
      "/": "baga6ea4seaqdat5c5ev7iyrnclt6vf3hjep7rqo2wbtespgdq3ioqkcwp23dwly"
    },
    "pieceSize": 34359738368,
    "termMin": 520000,
    "termMax": 779200,
    "expiration": 4141368,
    "height": 4126971
  },
  {
    "id": 69875251,
    "clientId": 2661434,
    "providerId": 3079766,
    "pieceCid": {
      "/": "baga6ea4seaqeo2hbvbvfquaghygy4t73wvbf2yusrlkre3gmgtfllzif65cmeii"
    },
    "pieceSize": 34359738368,
    "termMin": 520000,
    "termMax": 779200,
    "expiration": 4141368,
    "height": 4126971
  },
  {
    "id": 69875250,
    "clientId": 2661434,
    "providerId": 3079766,
    "pieceCid": {
      "/": "baga6ea4seaqbbbtbq42v673x3nfuhmwxyaion7k6dqbwdnpibn5nft6j2nx6cgi"
    },
    "pieceSize": 34359738368,
    "termMin": 520000,
    "termMax": 779200,
    "expiration": 4141356,
    "height": 4126971
  },
  {
    "id": 69875507,
    "clientId": 2661434,
    "providerId": 3079766,
    "pieceCid": {
      "/": "baga6ea4seaqfnsgoikihjrhvgj7iwlcevlfqgrzyusszioqiuwhm4yvdbr5c2jq"
    },
    "pieceSize": 34359738368,
    "termMin": 520000,
    "termMax": 779200,
    "expiration": 4141358,
    "height": 4126977
  },
  {
    "id": 69875506,
    "clientId": 2661434,
    "providerId": 3079766,
    "pieceCid": {
      "/": "baga6ea4seaqi3yj5esld6erqtqlfol3rstp7dn52z5tgcl67iaql22paqbiwyaq"
    },
    "pieceSize": 34359738368,
    "termMin": 520000,
    "termMax": 779200,
    "expiration": 4141358,
    "height": 4126977
  },
  {
    "id": 69875505,
    "clientId": 2661434,
    "providerId": 3079766,
    "pieceCid": {
      "/": "baga6ea4seaqnstnxntwfd57qgxog5nyyj2gzwqv7hcqhum2zf6sfbsti4f3m2aq"
    },
    "pieceSize": 34359738368,
    "termMin": 520000,
    "termMax": 779200,
    "expiration": 4141359,
    "height": 4126977
  },
  {
    "id": 69875504,
    "clientId": 2661434,
    "providerId": 3079766,
    "pieceCid": {
      "/": "baga6ea4seaqip637nqkzr65gtb5bkao4p2mjhnj6nuw3lvfycynpf7gl2aa74by"
    },
    "pieceSize": 34359738368,
    "termMin": 520000,
    "termMax": 779200,
    "expiration": 4141359,
    "height": 4126977
  },
  {
    "id": 69875503,
    "clientId": 2661434,
    "providerId": 3079766,
    "pieceCid": {
      "/": "baga6ea4seaqiuadtd5miyrludpoheutbi6ikvtandstfsiqwvytt6tuxoeoymma"
    },
    "pieceSize": 34359738368,
    "termMin": 520000,
    "termMax": 779200,
    "expiration": 4141358,
    "height": 4126977
  },
  {
    "id": 69875502,
    "clientId": 2661434,
    "providerId": 3079766,
    "pieceCid": {
      "/": "baga6ea4seaqfuq7bbecelc4jniiuh4rnhkodnhxdgn3aoihzmawmsrnwqddfsby"
    },
    "pieceSize": 34359738368,
    "termMin": 520000,
    "termMax": 779200,
    "expiration": 4141358,
    "height": 4126977
  },
  {
    "id": 69875501,
    "clientId": 2661434,
    "providerId": 3079766,
    "pieceCid": {
      "/": "baga6ea4seaqjuds3hl2udmoolisexfumrq4w23nxsbixmlb4oqgitr23v2hvmpq"
    },
    "pieceSize": 34359738368,
    "termMin": 520000,
    "termMax": 779200,
    "expiration": 4141359,
    "height": 4126977
  },
  {
    "id": 69875500,
    "clientId": 2661434,
    "providerId": 3079766,
    "pieceCid": {
      "/": "baga6ea4seaqdxheerk5bcsiv4vpmwri42r4dvwx6tpptv2nkxivetghddkjreci"
    },
    "pieceSize": 34359738368,
    "termMin": 520000,
    "termMax": 779200,
    "expiration": 4141369,
    "height": 4126977
  },
  {
    "id": 69875770,
    "clientId": 2661434,
    "providerId": 3079766,
    "pieceCid": {
      "/": "baga6ea4seaqesuuv65eofam6mj2n2b73dysgbo7yvvutces5gc7fu3nat2lcify"
    },
    "pieceSize": 34359738368,
    "termMin": 520000,
    "termMax": 779200,
    "expiration": 4141370,
    "height": 4126983
  },
  {
    "id": 69875769,
    "clientId": 2661434,
    "providerId": 3079766,
    "pieceCid": {
      "/": "baga6ea4seaqd53tsvbk7hons5z7f75eibpuqopnnd752yh4j62aswnswnsfqsci"
    },
    "pieceSize": 34359738368,
    "termMin": 520000,
    "termMax": 779200,
    "expiration": 4141370,
    "height": 4126983
  },
  {
    "id": 69875768,
    "clientId": 2661434,
    "providerId": 3079766,
    "pieceCid": {
      "/": "baga6ea4seaqa45eiunqiculfopxhwtzxmqhghjdahn2do34b5eswlrcy4hb2wby"
    },
    "pieceSize": 34359738368,
    "termMin": 520000,
    "termMax": 779200,
    "expiration": 4141371,
    "height": 4126983
  },
  {
    "id": 69875767,
    "clientId": 2661434,
    "providerId": 3079766,
    "pieceCid": {
      "/": "baga6ea4seaqeh47d7xb4yts6asqkbx3jnzfrxr4mxctvxvw2fa4belzvdnkaqhi"
    },
    "pieceSize": 34359738368,
    "termMin": 520000,
    "termMax": 779200,
    "expiration": 4141370,
    "height": 4126983
  },
  {
    "id": 69875766,
    "clientId": 2661434,
    "providerId": 3079766,
    "pieceCid": {
      "/": "baga6ea4seaqkgkj4l5egnwea6gmta7nfdq4xylq23nws7hhe5bz7hw3wj7jlycy"
    },
    "pieceSize": 34359738368,
    "termMin": 520000,
    "termMax": 779200,
    "expiration": 4141371,
    "height": 4126983
  },
  {
    "id": 69875765,
    "clientId": 2661434,
    "providerId": 3079766,
    "pieceCid": {
      "/": "baga6ea4seaqbgaaa42bbaziiv6yvas4e34mqdvtwzhtek6aecxtscerlz6ab2ka"
    },
    "pieceSize": 34359738368,
    "termMin": 520000,
    "termMax": 779200,
    "expiration": 4141370,
    "height": 4126983
  },
  {
    "id": 69875764,
    "clientId": 2661434,
    "providerId": 3079766,
    "pieceCid": {
      "/": "baga6ea4seaqoqizoti2f4ccu4nqtoufl3w7rrg76ugxpervkjpxcliw5zoagyjy"
    },
    "pieceSize": 34359738368,
    "termMin": 520000,
    "termMax": 779200,
    "expiration": 4141371,
    "height": 4126983
  },
  {
    "id": 69875763,
    "clientId": 2661434,
    "providerId": 3079766,
    "pieceCid": {
      "/": "baga6ea4seaqgupa6kkhsgxj5o2pmalexo57zy4pfxj465wg6fksh3hyczxlpmmi"
    },
    "pieceSize": 34359738368,
    "termMin": 520000,
    "termMax": 779200,
    "expiration": 4141370,
    "height": 4126983
  },
  {
    "id": 69875927,
    "clientId": 2661434,
    "providerId": 3079766,
    "pieceCid": {
      "/": "baga6ea4seaqkltj5e66c5xoqjhrwbjxcmroakoteoatmevylbid4bhzsbe4vepi"
    },
    "pieceSize": 34359738368,
    "termMin": 520000,
    "termMax": 779200,
    "expiration": 4141381,
    "height": 4126988
  },
  {
    "id": 69875926,
    "clientId": 2661434,
    "providerId": 3079766,
    "pieceCid": {
      "/": "baga6ea4seaqpnx3hs3mrr3uau3ftrse3mrg6ev2w2og35jr555rhx4udberauly"
    },
    "pieceSize": 34359738368,
    "termMin": 520000,
    "termMax": 779200,
    "expiration": 4141380,
    "height": 4126988
  },
  {
    "id": 69875925,
    "clientId": 2661434,
    "providerId": 3079766,
    "pieceCid": {
      "/": "baga6ea4seaqktv6cwbqmqcbutiw2um7utsqs7k3jed726hhfwvfir65tvz6weii"
    },
    "pieceSize": 34359738368,
    "termMin": 520000,
    "termMax": 779200,
    "expiration": 4141382,
    "height": 4126988
  },
  {
    "id": 69875924,
    "clientId": 2661434,
    "providerId": 3079766,
    "pieceCid": {
      "/": "baga6ea4seaqcaswqmye2a7ajziff7v7ppuqniffo53cqbpvdbd5x5nr2jxskqpa"
    },
    "pieceSize": 34359738368,
    "termMin": 520000,
    "termMax": 779200,
    "expiration": 4141381,
    "height": 4126988
  },
  {
    "id": 69875923,
    "clientId": 2661434,
    "providerId": 3079766,
    "pieceCid": {
      "/": "baga6ea4seaqdzo6xsbfnmajqeqynhcezemgu6weaiayspohgevkx6sz62skdodq"
    },
    "pieceSize": 34359738368,
    "termMin": 520000,
    "termMax": 779200,
    "expiration": 4141381,
    "height": 4126988
  },
  {
    "id": 69875922,
    "clientId": 2661434,
    "providerId": 3079766,
    "pieceCid": {
      "/": "baga6ea4seaqcipkvc5vqz3suylqqoy2knui7wbcvy25666a3ipkb7joolis5uoq"
    },
    "pieceSize": 34359738368,
    "termMin": 520000,
    "termMax": 779200,
    "expiration": 4141381,
    "height": 4126988
  },
  {
    "id": 69875921,
    "clientId": 2661434,
    "providerId": 3079766,
    "pieceCid": {
      "/": "baga6ea4seaqbfrqns322tm6tmzecxc5j4hf2z3kpftt3id7lc72bpnrjcay6wgy"
    },
    "pieceSize": 34359738368,
    "termMin": 520000,
    "termMax": 779200,
    "expiration": 4141381,
    "height": 4126988
  },
  {
    "id": 69875920,
    "clientId": 2661434,
    "providerId": 3079766,
    "pieceCid": {
      "/": "baga6ea4seaqeuf62kaqwx5b3kl5ugqex5k3maupu4klassqlkxt2pwo3bnh7gmi"
    },
    "pieceSize": 34359738368,
    "termMin": 520000,
    "termMax": 779200,
    "expiration": 4141380,
    "height": 4126988
  },
  {
    "id": 69876345,
    "clientId": 2661434,
    "providerId": 3079766,
    "pieceCid": {
      "/": "baga6ea4seaqjfeoxeimg4dlq3miqyrd3pqppkdlycch3qcogpmwqfyt25bjmupy"
    },
    "pieceSize": 34359738368,
    "termMin": 520000,
    "termMax": 779200,
    "expiration": 4141397,
    "height": 4126998
  },
  {
    "id": 69876344,
    "clientId": 2661434,
    "providerId": 3079766,
    "pieceCid": {
      "/": "baga6ea4seaqeozbae3fdkk75h3ksvumc6es7en2kceexpkt2znbh5ia5gqxkwna"
    },
    "pieceSize": 34359738368,
    "termMin": 520000,
    "termMax": 779200,
    "expiration": 4141397,
    "height": 4126998
  },
  {
    "id": 69876343,
    "clientId": 2661434,
    "providerId": 3079766,
    "pieceCid": {
      "/": "baga6ea4seaqh2pdchwpdp3wiypojldh5dmbacj4kcpgdmlstlolqaq4irmp7aiy"
    },
    "pieceSize": 34359738368,
    "termMin": 520000,
    "termMax": 779200,
    "expiration": 4141397,
    "height": 4126998
  },
  {
    "id": 69876342,
    "clientId": 2661434,
    "providerId": 3079766,
    "pieceCid": {
      "/": "baga6ea4seaqdkp72xgqrfl4ziwoxts3fpnf522zptjtdczhrbubtvsqvd2upaca"
    },
    "pieceSize": 34359738368,
    "termMin": 520000,
    "termMax": 779200,
    "expiration": 4141397,
    "height": 4126998
  },
  {
    "id": 69876341,
    "clientId": 2661434,
    "providerId": 3079766,
    "pieceCid": {
      "/": "baga6ea4seaqamswqo2jhzwdmvb4bt3p4aqq47qezdsqlo7kmtdiysurv2nfmugy"
    },
    "pieceSize": 34359738368,
    "termMin": 520000,
    "termMax": 779200,
    "expiration": 4141397,
    "height": 4126998
  },
  {
    "id": 69876340,
    "clientId": 2661434,
    "providerId": 3079766,
    "pieceCid": {
      "/": "baga6ea4seaqmvq4t754mo5mf3ufbheumijuzs6negnjc2o56az7ub7dahl5i2ay"
    },
    "pieceSize": 34359738368,
    "termMin": 520000,
    "termMax": 779200,
    "expiration": 4141396,
    "height": 4126998
  },
  {
    "id": 69876339,
    "clientId": 2661434,
    "providerId": 3079766,
    "pieceCid": {
      "/": "baga6ea4seaqcm32svve7quscwf5k5za6eqpyrq6u5yddr5luiycknuqvlsefsba"
    },
    "pieceSize": 34359738368,
    "termMin": 520000,
    "termMax": 779200,
    "expiration": 4141396,
    "height": 4126998
  },
  {
    "id": 69876338,
    "clientId": 2661434,
    "providerId": 3079766,
    "pieceCid": {
      "/": "baga6ea4seaqd27pywxuumowuf3vog5sjvni4gycsnj2vijyf6vm7npjvyfn7qia"
    },
    "pieceSize": 34359738368,
    "termMin": 520000,
    "termMax": 779200,
    "expiration": 4141380,
    "height": 4126998
  },
  {
    "id": 69876413,
    "clientId": 2661434,
    "providerId": 3079766,
    "pieceCid": {
      "/": "baga6ea4seaqljlc7xuxsowov3e22ifi4ivmbp6j4j2ldoc7iosbrh37n5tnmebi"
    },
    "pieceSize": 34359738368,
    "termMin": 520000,
    "termMax": 779200,
    "expiration": 4141383,
    "height": 4127000
  },
  {
    "id": 69876412,
    "clientId": 2661434,
    "providerId": 3079766,
    "pieceCid": {
      "/": "baga6ea4seaqovvum4rxrp2oygcgrcqcj5u7aqetesz45lu4iog2fypwk6xdpopy"
    },
    "pieceSize": 34359738368,
    "termMin": 520000,
    "termMax": 779200,
    "expiration": 4141383,
    "height": 4127000
  },
  {
    "id": 69876411,
    "clientId": 2661434,
    "providerId": 3079766,
    "pieceCid": {
      "/": "baga6ea4seaqii33tumgcvnygpd4h3gcnqaxygnwzyh3tbzwxy6kv5v36xgow2ea"
    },
    "pieceSize": 34359738368,
    "termMin": 520000,
    "termMax": 779200,
    "expiration": 4141382,
    "height": 4127000
  },
  {
    "id": 69876410,
    "clientId": 2661434,
    "providerId": 3079766,
    "pieceCid": {
      "/": "baga6ea4seaqgi3bxdx4qjj3xfvteay2agg3bprdhaarxphs6zma2iemppfdm2iy"
    },
    "pieceSize": 34359738368,
    "termMin": 520000,
    "termMax": 779200,
    "expiration": 4141382,
    "height": 4127000
  },
  {
    "id": 69876409,
    "clientId": 2661434,
    "providerId": 3079766,
    "pieceCid": {
      "/": "baga6ea4seaqebjawznzo5ggev7un4xw5t44wof4h5yxff3xy2cepfu3mbamymhy"
    },
    "pieceSize": 34359738368,
    "termMin": 520000,
    "termMax": 779200,
    "expiration": 4141382,
    "height": 4127000
  },
  {
    "id": 69876408,
    "clientId": 2661434,
    "providerId": 3079766,
    "pieceCid": {
      "/": "baga6ea4seaqfqyk4qqci7hi27tdfgjtjqduiashamlcmyc2nwqivljcbuerwscq"
    },
    "pieceSize": 34359738368,
    "termMin": 520000,
    "termMax": 779200,
    "expiration": 4141383,
    "height": 4127000
  },
  {
    "id": 69876407,
    "clientId": 2661434,
    "providerId": 3079766,
    "pieceCid": {
      "/": "baga6ea4seaqb622kgln47vvk56y6wv4q5wyjc2tbb4fjd4fwtbpvtc7dfaahgly"
    },
    "pieceSize": 34359738368,
    "termMin": 520000,
    "termMax": 779200,
    "expiration": 4141382,
    "height": 4127000
  },
  {
    "id": 69876406,
    "clientId": 2661434,
    "providerId": 3079766,
    "pieceCid": {
      "/": "baga6ea4seaqm6ukxja5hilu3f2tzcyxp35hqfsuxht3gjl3yt6dewjpr3ssu4oi"
    },
    "pieceSize": 34359738368,
    "termMin": 520000,
    "termMax": 779200,
    "expiration": 4141398,
    "height": 4127000
  },
  {
    "id": 69876837,
    "clientId": 2661434,
    "providerId": 3079766,
    "pieceCid": {
      "/": "baga6ea4seaqgrxpr6uxgz7ip67g35wtoy746vbkral4m65mdj5al36r537b3caa"
    },
    "pieceSize": 34359738368,
    "termMin": 520000,
    "termMax": 779200,
    "expiration": 4141398,
    "height": 4127012
  },
  {
    "id": 69876836,
    "clientId": 2661434,
    "providerId": 3079766,
    "pieceCid": {
      "/": "baga6ea4seaqdlr7lkfptciptipr3tge3qzybdttjkk34p3pky4zemgsgvkyaaey"
    },
    "pieceSize": 34359738368,
    "termMin": 520000,
    "termMax": 779200,
    "expiration": 4141399,
    "height": 4127012
  },
  {
    "id": 69876835,
    "clientId": 2661434,
    "providerId": 3079766,
    "pieceCid": {
      "/": "baga6ea4seaqasxmcks56nnc7rm3dgstfpuxv4w3kbfzd75y65luwoeuzl5qjemq"
    },
    "pieceSize": 34359738368,
    "termMin": 520000,
    "termMax": 779200,
    "expiration": 4141399,
    "height": 4127012
  },
  {
    "id": 69876834,
    "clientId": 2661434,
    "providerId": 3079766,
    "pieceCid": {
      "/": "baga6ea4seaqlsr5pnnmc2sdd7uoqre2k4mcptyh3i3nz2nmp2437ccbgnojjefy"
    },
    "pieceSize": 34359738368,
    "termMin": 520000,
    "termMax": 779200,
    "expiration": 4141398,
    "height": 4127012
  },
  {
    "id": 69876833,
    "clientId": 2661434,
    "providerId": 3079766,
    "pieceCid": {
      "/": "baga6ea4seaqa6pwwqeiwxyaydhpy6olhn3a5g2tfuujno6yoycpwe4ol7dhdooy"
    },
    "pieceSize": 34359738368,
    "termMin": 520000,
    "termMax": 779200,
    "expiration": 4141399,
    "height": 4127012
  },
  {
    "id": 69876832,
    "clientId": 2661434,
    "providerId": 3079766,
    "pieceCid": {
      "/": "baga6ea4seaqf6fzjcepzd6gdckbdypcsft6gradh47dttn7lacw5fna3jf2zqni"
    },
    "pieceSize": 34359738368,
    "termMin": 520000,
    "termMax": 779200,
    "expiration": 4141398,
    "height": 4127012
  },
  {
    "id": 69876831,
    "clientId": 2661434,
    "providerId": 3079766,
    "pieceCid": {
      "/": "baga6ea4seaqpjlepeniaugyzflbdcs354rwtwnbsgvizmrxgt5ksqxqjiw3dily"
    },
    "pieceSize": 34359738368,
    "termMin": 520000,
    "termMax": 779200,
    "expiration": 4141398,
    "height": 4127012
  },
  {
    "id": 69876830,
    "clientId": 2661434,
    "providerId": 3079766,
    "pieceCid": {
      "/": "baga6ea4seaqisnazeprttwwuurjd5hglfonxyazwan77bikr65wbscik6lda4di"
    },
    "pieceSize": 34359738368,
    "termMin": 520000,
    "termMax": 779200,
    "expiration": 4141399,
    "height": 4127012
  },
  {
    "id": 69877070,
    "clientId": 2661434,
    "providerId": 3079766,
    "pieceCid": {
      "/": "baga6ea4seaqd674lyg4fnzsv4axldmfpiz33ml3onufyshl7ztjezkhptuqe6oa"
    },
    "pieceSize": 34359738368,
    "termMin": 520000,
    "termMax": 779200,
    "expiration": 4141410,
    "height": 4127018
  },
  {
    "id": 69877069,
    "clientId": 2661434,
    "providerId": 3079766,
    "pieceCid": {
      "/": "baga6ea4seaqjfpmoiymll2n5g7najexmfdgltw53s5kkwn4cl5pd2nso44a3aci"
    },
    "pieceSize": 34359738368,
    "termMin": 520000,
    "termMax": 779200,
    "expiration": 4141411,
    "height": 4127018
  },
  {
    "id": 69877068,
    "clientId": 2661434,
    "providerId": 3079766,
    "pieceCid": {
      "/": "baga6ea4seaqeoa5kyf32rgml2gyfedl3x6m6s3ozz2z3nf2apcnwo44q3mxfkjy"
    },
    "pieceSize": 34359738368,
    "termMin": 520000,
    "termMax": 779200,
    "expiration": 4141409,
    "height": 4127018
  },
  {
    "id": 69877067,
    "clientId": 2661434,
    "providerId": 3079766,
    "pieceCid": {
      "/": "baga6ea4seaqefodwzzbzzgcbi4pbovtnzrm4ak4yxd4ndj7bw5iegbabv67nqoi"
    },
    "pieceSize": 34359738368,
    "termMin": 520000,
    "termMax": 779200,
    "expiration": 4141409,
    "height": 4127018
  },
  {
    "id": 69877066,
    "clientId": 2661434,
    "providerId": 3079766,
    "pieceCid": {
      "/": "baga6ea4seaqlkjqji3qywhi4k2on4shetwgawe73xubzn4yxf4nfzjit2gobqgy"
    },
    "pieceSize": 34359738368,
    "termMin": 520000,
    "termMax": 779200,
    "expiration": 4141410,
    "height": 4127018
  },
  {
    "id": 69877065,
    "clientId": 2661434,
    "providerId": 3079766,
    "pieceCid": {
      "/": "baga6ea4seaqa6bj5tlvoewlvl25p5sb3d5jvk2az346tafvuashq5d7f72lxima"
    },
    "pieceSize": 34359738368,
    "termMin": 520000,
    "termMax": 779200,
    "expiration": 4141409,
    "height": 4127018
  },
  {
    "id": 69877064,
    "clientId": 2661434,
    "providerId": 3079766,
    "pieceCid": {
      "/": "baga6ea4seaqo25ijjnccp4eqtkfed4k3qfxmtt2hedx5ocpexn5re2bdsuogwaq"
    },
    "pieceSize": 34359738368,
    "termMin": 520000,
    "termMax": 779200,
    "expiration": 4141409,
    "height": 4127018
  },
  {
    "id": 69877063,
    "clientId": 2661434,
    "providerId": 3079766,
    "pieceCid": {
      "/": "baga6ea4seaqk3pqyqotpb5a64p73basnfas5s63mton5wghfp3pwkculotrxkea"
    },
    "pieceSize": 34359738368,
    "termMin": 520000,
    "termMax": 779200,
    "expiration": 4141411,
    "height": 4127018
  },
  {
    "id": 69877241,
    "clientId": 2661434,
    "providerId": 3079766,
    "pieceCid": {
      "/": "baga6ea4seaqe57ftih3tcnnt75dfthwsxeevzprh5rydzcgjspvymcc7t66toji"
    },
    "pieceSize": 34359738368,
    "termMin": 520000,
    "termMax": 779200,
    "expiration": 4141408,
    "height": 4127023
  },
  {
    "id": 69877240,
    "clientId": 2661434,
    "providerId": 3079766,
    "pieceCid": {
      "/": "baga6ea4seaqc663qfr6jhhurvo5hhzqeebfzwhuigpkoae6fezxolonzwr4guky"
    },
    "pieceSize": 34359738368,
    "termMin": 520000,
    "termMax": 779200,
    "expiration": 4141410,
    "height": 4127023
  },
  {
    "id": 69877239,
    "clientId": 2661434,
    "providerId": 3079766,
    "pieceCid": {
      "/": "baga6ea4seaqgkxs5bhc5iwvyugizsdzq2uvidiy4p4hffrqii3qalxa4z7mzumq"
    },
    "pieceSize": 34359738368,
    "termMin": 520000,
    "termMax": 779200,
    "expiration": 4141411,
    "height": 4127023
  },
  {
    "id": 69877238,
    "clientId": 2661434,
    "providerId": 3079766,
    "pieceCid": {
      "/": "baga6ea4seaqa4lvjw4f4p2q257aj5guabozrr6bfb4iknfumegtpm52cht2pyfa"
    },
    "pieceSize": 34359738368,
    "termMin": 520000,
    "termMax": 779200,
    "expiration": 4141410,
    "height": 4127023
  },
  {
    "id": 69877237,
    "clientId": 2661434,
    "providerId": 3079766,
    "pieceCid": {
      "/": "baga6ea4seaqpwkrizg3dfsmpsepbtssicuamxb757cyzadeyz2wwnmu5tje2kpa"
    },
    "pieceSize": 34359738368,
    "termMin": 520000,
    "termMax": 779200,
    "expiration": 4141409,
    "height": 4127023
  },
  {
    "id": 69877236,
    "clientId": 2661434,
    "providerId": 3079766,
    "pieceCid": {
      "/": "baga6ea4seaqaivl4iulz5frrxpd7nxph6rcbx7h4ecl6agaziot4kj4jygp6yaa"
    },
    "pieceSize": 34359738368,
    "termMin": 520000,
    "termMax": 779200,
    "expiration": 4141410,
    "height": 4127023
  },
  {
    "id": 69877235,
    "clientId": 2661434,
    "providerId": 3079766,
    "pieceCid": {
      "/": "baga6ea4seaqon4jxaaukz564febmldwf23d5cmbdmgqwhou5vvdk7js6ig4imai"
    },
    "pieceSize": 34359738368,
    "termMin": 520000,
    "termMax": 779200,
    "expiration": 4141410,
    "height": 4127023
  },
  {
    "id": 69877234,
    "clientId": 2661434,
    "providerId": 3079766,
    "pieceCid": {
      "/": "baga6ea4seaqb2de7d5rgfgk4s5zawhqgvtqn5s727zitw5ddvkegjmek7smpihi"
    },
    "pieceSize": 34359738368,
    "termMin": 520000,
    "termMax": 779200,
    "expiration": 4141408,
    "height": 4127023
  },
  {
    "id": 69877654,
    "clientId": 2661434,
    "providerId": 3079766,
    "pieceCid": {
      "/": "baga6ea4seaqc4vrdsxer5gj6vp5doz3j2commshufrkvxl2zyxbvqpx2vbimima"
    },
    "pieceSize": 34359738368,
    "termMin": 520000,
    "termMax": 779200,
    "expiration": 4141425,
    "height": 4127033
  },
  {
    "id": 69877653,
    "clientId": 2661434,
    "providerId": 3079766,
    "pieceCid": {
      "/": "baga6ea4seaqfss3gwxy3veaqh4tyhiwvbxiexmpel2mxkkqjw2puhanvy4siqhq"
    },
    "pieceSize": 34359738368,
    "termMin": 520000,
    "termMax": 779200,
    "expiration": 4141426,
    "height": 4127033
  },
  {
    "id": 69877652,
    "clientId": 2661434,
    "providerId": 3079766,
    "pieceCid": {
      "/": "baga6ea4seaqnvlsuvknylvr7pbtzxon5i4mh64zl3xffpak4o3hcze56y7blgdq"
    },
    "pieceSize": 34359738368,
    "termMin": 520000,
    "termMax": 779200,
    "expiration": 4141425,
    "height": 4127033
  },
  {
    "id": 69877651,
    "clientId": 2661434,
    "providerId": 3079766,
    "pieceCid": {
      "/": "baga6ea4seaqde7mh26k3u2zspegvnp4ejvgta56fm6sbolkdzhthaudn7gjnykq"
    },
    "pieceSize": 34359738368,
    "termMin": 520000,
    "termMax": 779200,
    "expiration": 4141426,
    "height": 4127033
  },
  {
    "id": 69877650,
    "clientId": 2661434,
    "providerId": 3079766,
    "pieceCid": {
      "/": "baga6ea4seaqkivslfiesreou7ynh3ylzrs7cbcbhmgxxmwkw227dcj4ckuj32ia"
    },
    "pieceSize": 34359738368,
    "termMin": 520000,
    "termMax": 779200,
    "expiration": 4141425,
    "height": 4127033
  },
  {
    "id": 69877649,
    "clientId": 2661434,
    "providerId": 3079766,
    "pieceCid": {
      "/": "baga6ea4seaqdxxbhvggsf64i4sxadrkirt4fxu5i3e6pby576hglxsgz23qlaea"
    },
    "pieceSize": 34359738368,
    "termMin": 520000,
    "termMax": 779200,
    "expiration": 4141425,
    "height": 4127033
  },
  {
    "id": 69877648,
    "clientId": 2661434,
    "providerId": 3079766,
    "pieceCid": {
      "/": "baga6ea4seaqi22j2er3qevl3shbaaizxbtpbaxc2i2ukknxur6tdgrxcvbwpkly"
    },
    "pieceSize": 34359738368,
    "termMin": 520000,
    "termMax": 779200,
    "expiration": 4141425,
    "height": 4127033
  },
  {
    "id": 69877647,
    "clientId": 2661434,
    "providerId": 3079766,
    "pieceCid": {
      "/": "baga6ea4seaqhe6skgcavi3zlauzmrpgm4loermwv2bmpwoiaegpokzhjj3s7oji"
    },
    "pieceSize": 34359738368,
    "termMin": 520000,
    "termMax": 779200,
    "expiration": 4141425,
    "height": 4127033
  },
  {
    "id": 69877914,
    "clientId": 2661434,
    "providerId": 3079766,
    "pieceCid": {
      "/": "baga6ea4seaql2caip6lxnj46o3fbiwwx7ottzkz5egzem4f75pgbnkccbbivkcy"
    },
    "pieceSize": 34359738368,
    "termMin": 520000,
    "termMax": 779200,
    "expiration": 4141438,
    "height": 4127040
  },
  {
    "id": 69877913,
    "clientId": 2661434,
    "providerId": 3079766,
    "pieceCid": {
      "/": "baga6ea4seaqose5v26jasmlrtzyjlgsxtq23wnwnjnht6fvyyy6f7hpmvrmt2ha"
    },
    "pieceSize": 34359738368,
    "termMin": 520000,
    "termMax": 779200,
    "expiration": 4141437,
    "height": 4127040
  },
  {
    "id": 69877912,
    "clientId": 2661434,
    "providerId": 3079766,
    "pieceCid": {
      "/": "baga6ea4seaqoka7tikiggoe2n3shmcu2kumuztjndoouiokmvjtij7d4mr2vmjq"
    },
    "pieceSize": 34359738368,
    "termMin": 520000,
    "termMax": 779200,
    "expiration": 4141437,
    "height": 4127040
  },
  {
    "id": 69877911,
    "clientId": 2661434,
    "providerId": 3079766,
    "pieceCid": {
      "/": "baga6ea4seaqhsn5op7ytekmjxolwajwdo5b4iz7euxhyqdh6meqwdq4bvaa34ay"
    },
    "pieceSize": 34359738368,
    "termMin": 520000,
    "termMax": 779200,
    "expiration": 4141437,
    "height": 4127040
  },
  {
    "id": 69877910,
    "clientId": 2661434,
    "providerId": 3079766,
    "pieceCid": {
      "/": "baga6ea4seaqjxt4phq47to75cfbqbtqzepzl2a7ymmfum23aov3b7ph5v6tvkoy"
    },
    "pieceSize": 34359738368,
    "termMin": 520000,
    "termMax": 779200,
    "expiration": 4141437,
    "height": 4127040
  },
  {
    "id": 69877909,
    "clientId": 2661434,
    "providerId": 3079766,
    "pieceCid": {
      "/": "baga6ea4seaqiixiuaepup2maz7iqsv2qogruytcqfnuunbwtadaiolgkkte6qhq"
    },
    "pieceSize": 34359738368,
    "termMin": 520000,
    "termMax": 779200,
    "expiration": 4141437,
    "height": 4127040
  },
  {
    "id": 69877908,
    "clientId": 2661434,
    "providerId": 3079766,
    "pieceCid": {
      "/": "baga6ea4seaqkwvhzutv6w7jwgmlyhasbx2m5vzqcxi5ehgt2qvyq4b7uuu54wha"
    },
    "pieceSize": 34359738368,
    "termMin": 520000,
    "termMax": 779200,
    "expiration": 4141437,
    "height": 4127040
  },
  {
    "id": 69877907,
    "clientId": 2661434,
    "providerId": 3079766,
    "pieceCid": {
      "/": "baga6ea4seaqfgdhvn77gikklcgw3wk2lnmw22qblolytfyijuhxwlpu2qufumlq"
    },
    "pieceSize": 34359738368,
    "termMin": 520000,
    "termMax": 779200,
    "expiration": 4141424,
    "height": 4127040
  },
  {
    "id": 69878169,
    "clientId": 2661434,
    "providerId": 3079766,
    "pieceCid": {
      "/": "baga6ea4seaqgriiqbpzehjr5k3robdiqrkndou7aahvnydptjzwmr34x2tcvkji"
    },
    "pieceSize": 34359738368,
    "termMin": 520000,
    "termMax": 779200,
    "expiration": 4141426,
    "height": 4127045
  },
  {
    "id": 69878168,
    "clientId": 2661434,
    "providerId": 3079766,
    "pieceCid": {
      "/": "baga6ea4seaqip22j7gvkzpn65clcnd3n4uv2ozmnikpfmo4jlyx4wstidz4c2hi"
    },
    "pieceSize": 34359738368,
    "termMin": 520000,
    "termMax": 779200,
    "expiration": 4141426,
    "height": 4127045
  },
  {
    "id": 69878167,
    "clientId": 2661434,
    "providerId": 3079766,
    "pieceCid": {
      "/": "baga6ea4seaqfoqjp6qq2ppixhc63guak4erm7g5xaszsemuiwipyjimqwpqcqey"
    },
    "pieceSize": 34359738368,
    "termMin": 520000,
    "termMax": 779200,
    "expiration": 4141426,
    "height": 4127045
  },
  {
    "id": 69878166,
    "clientId": 2661434,
    "providerId": 3079766,
    "pieceCid": {
      "/": "baga6ea4seaqfyh5ksxv3akgxjrx45asifwlhi4z7gch4qgvd3ydrcltt4dyxuma"
    },
    "pieceSize": 34359738368,
    "termMin": 520000,
    "termMax": 779200,
    "expiration": 4141427,
    "height": 4127045
  },
  {
    "id": 69878165,
    "clientId": 2661434,
    "providerId": 3079766,
    "pieceCid": {
      "/": "baga6ea4seaqj67ry7dshmhx36l6fl5eqr23vviww7islkvn2hho6mzehvumfgli"
    },
    "pieceSize": 34359738368,
    "termMin": 520000,
    "termMax": 779200,
    "expiration": 4141427,
    "height": 4127045
  },
  {
    "id": 69878164,
    "clientId": 2661434,
    "providerId": 3079766,
    "pieceCid": {
      "/": "baga6ea4seaqisen7ezx2jni5qvvdmranzprmfr2i7xysydb5g7rb6njlflvmuaa"
    },
    "pieceSize": 34359738368,
    "termMin": 520000,
    "termMax": 779200,
    "expiration": 4141427,
    "height": 4127045
  },
  {
    "id": 69878163,
    "clientId": 2661434,
    "providerId": 3079766,
    "pieceCid": {
      "/": "baga6ea4seaqpwt5gekcd5pzx7t5sugnsouijw52p6jf4bvpp6hzka6darz45ipi"
    },
    "pieceSize": 34359738368,
    "termMin": 520000,
    "termMax": 779200,
    "expiration": 4141427,
    "height": 4127045
  },
  {
    "id": 69878162,
    "clientId": 2661434,
    "providerId": 3079766,
    "pieceCid": {
      "/": "baga6ea4seaql4lxfofhrpl5jbo566gypmqg3cw6tgsojt3w3vflsqrqdsd6l6gi"
    },
    "pieceSize": 34359738368,
    "termMin": 520000,
    "termMax": 779200,
    "expiration": 4141436,
    "height": 4127045
  },
  {
    "id": 69878404,
    "clientId": 2661434,
    "providerId": 3079766,
    "pieceCid": {
      "/": "baga6ea4seaqnkh7yr6oh4o5l27aiymfdkwy4bko5e2pwypcmh3f53rd2iudsqay"
    },
    "pieceSize": 34359738368,
    "termMin": 520000,
    "termMax": 779200,
    "expiration": 4141438,
    "height": 4127052
  },
  {
    "id": 69878403,
    "clientId": 2661434,
    "providerId": 3079766,
    "pieceCid": {
      "/": "baga6ea4seaqb4newzpup5nwkxcgebagthosccrq7v5pib43xnoin4plaujcegdy"
    },
    "pieceSize": 34359738368,
    "termMin": 520000,
    "termMax": 779200,
    "expiration": 4141438,
    "height": 4127052
  },
  {
    "id": 69878402,
    "clientId": 2661434,
    "providerId": 3079766,
    "pieceCid": {
      "/": "baga6ea4seaqi4tdits5hm7l4ukfrkypwaxgdf73w3cgsjp3cwkumjx2eqjie6hy"
    },
    "pieceSize": 34359738368,
    "termMin": 520000,
    "termMax": 779200,
    "expiration": 4141438,
    "height": 4127052
  },
  {
    "id": 69878401,
    "clientId": 2661434,
    "providerId": 3079766,
    "pieceCid": {
      "/": "baga6ea4seaqi6yq4mk2z4xh5krl6tt33oejcwren25acnbkvnalnbwtanjyq2ca"
    },
    "pieceSize": 34359738368,
    "termMin": 520000,
    "termMax": 779200,
    "expiration": 4141438,
    "height": 4127052
  },
  {
    "id": 69878400,
    "clientId": 2661434,
    "providerId": 3079766,
    "pieceCid": {
      "/": "baga6ea4seaqnoxlen6k43osoulppt4wldlxitwlknqf2iwyic5mkmylzksyt6ni"
    },
    "pieceSize": 34359738368,
    "termMin": 520000,
    "termMax": 779200,
    "expiration": 4141439,
    "height": 4127052
  },
  {
    "id": 69878399,
    "clientId": 2661434,
    "providerId": 3079766,
    "pieceCid": {
      "/": "baga6ea4seaqjoruecngyydwbh7yejppjqd4k5ty4sayjdn3xgxscipouyy7qybi"
    },
    "pieceSize": 34359738368,
    "termMin": 520000,
    "termMax": 779200,
    "expiration": 4141439,
    "height": 4127052
  },
  {
    "id": 69878398,
    "clientId": 2661434,
    "providerId": 3079766,
    "pieceCid": {
      "/": "baga6ea4seaqec6ep3lrnu4bqzjv266sobkvzkxh763uovghmlulp2rkrswxb2ai"
    },
    "pieceSize": 34359738368,
    "termMin": 520000,
    "termMax": 779200,
    "expiration": 4141439,
    "height": 4127052
  },
  {
    "id": 69878397,
    "clientId": 2661434,
    "providerId": 3079766,
    "pieceCid": {
      "/": "baga6ea4seaqpsxtrn2rzyefddo3ajivolnil3325b6ho7ol67wzy7mvvmxv4ybi"
    },
    "pieceSize": 34359738368,
    "termMin": 520000,
    "termMax": 779200,
    "expiration": 4141439,
    "height": 4127052
  },
  {
    "id": 69878571,
    "clientId": 2661434,
    "providerId": 3079766,
    "pieceCid": {
      "/": "baga6ea4seaqa7xy3434htvrvnmsxh542fbvifdxqsi5lqysqnyoceccviq7hmpa"
    },
    "pieceSize": 34359738368,
    "termMin": 520000,
    "termMax": 779200,
    "expiration": 4141450,
    "height": 4127056
  },
  {
    "id": 69878570,
    "clientId": 2661434,
    "providerId": 3079766,
    "pieceCid": {
      "/": "baga6ea4seaqo7hlbhdwmyreczrfpip467r3yvs6hutiu5kfu7yylgsfk4nadcbq"
    },
    "pieceSize": 34359738368,
    "termMin": 520000,
    "termMax": 779200,
    "expiration": 4141448,
    "height": 4127056
  },
  {
    "id": 69878569,
    "clientId": 2661434,
    "providerId": 3079766,
    "pieceCid": {
      "/": "baga6ea4seaqigknucif74myaomt2af3kge5zlwrf7lbbzs23g2vrwj6d7za5yoi"
    },
    "pieceSize": 34359738368,
    "termMin": 520000,
    "termMax": 779200,
    "expiration": 4141450,
    "height": 4127056
  },
  {
    "id": 69878568,
    "clientId": 2661434,
    "providerId": 3079766,
    "pieceCid": {
      "/": "baga6ea4seaqhoorw3h6lce7qpzoxemodbdpuwhhy6blnybhauilztk7wtzlmcki"
    },
    "pieceSize": 34359738368,
    "termMin": 520000,
    "termMax": 779200,
    "expiration": 4141449,
    "height": 4127056
  },
  {
    "id": 69878567,
    "clientId": 2661434,
    "providerId": 3079766,
    "pieceCid": {
      "/": "baga6ea4seaqg3qg22l2hczzbr34kibj2p2gcgsu7yrvgik3x7d6xfmzcuto6kji"
    },
    "pieceSize": 34359738368,
    "termMin": 520000,
    "termMax": 779200,
    "expiration": 4141449,
    "height": 4127056
  },
  {
    "id": 69878566,
    "clientId": 2661434,
    "providerId": 3079766,
    "pieceCid": {
      "/": "baga6ea4seaqp5eo7yphare7cccj5ghlhrs5iocey2ymjo23wmzuc5tuwsjjx6ji"
    },
    "pieceSize": 34359738368,
    "termMin": 520000,
    "termMax": 779200,
    "expiration": 4141449,
    "height": 4127056
  },
  {
    "id": 69878565,
    "clientId": 2661434,
    "providerId": 3079766,
    "pieceCid": {
      "/": "baga6ea4seaqgt2ifpfibp5rxlvpqthiderbdddwe5l5arfdcaro7jdmowkcy6ci"
    },
    "pieceSize": 34359738368,
    "termMin": 520000,
    "termMax": 779200,
    "expiration": 4141449,
    "height": 4127056
  },
  {
    "id": 69878564,
    "clientId": 2661434,
    "providerId": 3079766,
    "pieceCid": {
      "/": "baga6ea4seaqeskscwucpn4rcogq3enhypant7npia7vnsz57gyjog5kjzvyi4aa"
    },
    "pieceSize": 34359738368,
    "termMin": 520000,
    "termMax": 779200,
    "expiration": 4141449,
    "height": 4127056
  },
  {
    "id": 69879017,
    "clientId": 2661434,
    "providerId": 3079766,
    "pieceCid": {
      "/": "baga6ea4seaqkg7jntxqifopj42do7h6a47rhqmuusjx2q4drryk4ecdy7ok5ena"
    },
    "pieceSize": 34359738368,
    "termMin": 520000,
    "termMax": 779200,
    "expiration": 4141466,
    "height": 4127067
  },
  {
    "id": 69879016,
    "clientId": 2661434,
    "providerId": 3079766,
    "pieceCid": {
      "/": "baga6ea4seaqbrsj2ccv674ibt7upkpd2vsbkkkmpmb64gpjujzyuouih2hvhchq"
    },
    "pieceSize": 34359738368,
    "termMin": 520000,
    "termMax": 779200,
    "expiration": 4141465,
    "height": 4127067
  },
  {
    "id": 69879015,
    "clientId": 2661434,
    "providerId": 3079766,
    "pieceCid": {
      "/": "baga6ea4seaqpnpr56toebr7l4tos6uwt5suvbczeaskceqcw7kssc6ttm6tl4hi"
    },
    "pieceSize": 34359738368,
    "termMin": 520000,
    "termMax": 779200,
    "expiration": 4141465,
    "height": 4127067
  },
  {
    "id": 69879014,
    "clientId": 2661434,
    "providerId": 3079766,
    "pieceCid": {
      "/": "baga6ea4seaqfnlj4hanofhzuoufw6ptojztgf5twn23amn3qeai7nh7yrck2cfy"
    },
    "pieceSize": 34359738368,
    "termMin": 520000,
    "termMax": 779200,
    "expiration": 4141465,
    "height": 4127067
  },
  {
    "id": 69879013,
    "clientId": 2661434,
    "providerId": 3079766,
    "pieceCid": {
      "/": "baga6ea4seaqjn5znggdbshh3hvexgqtksuf7shrhj6wcymozxya6wiuwdwmkuei"
    },
    "pieceSize": 34359738368,
    "termMin": 520000,
    "termMax": 779200,
    "expiration": 4141465,
    "height": 4127067
  },
  {
    "id": 69879012,
    "clientId": 2661434,
    "providerId": 3079766,
    "pieceCid": {
      "/": "baga6ea4seaqge42jccb7c4pplqxdcnrg2r4cej2twgwdi3asmrdgr5vyj4v2egq"
    },
    "pieceSize": 34359738368,
    "termMin": 520000,
    "termMax": 779200,
    "expiration": 4141465,
    "height": 4127067
  },
  {
    "id": 69879011,
    "clientId": 2661434,
    "providerId": 3079766,
    "pieceCid": {
      "/": "baga6ea4seaqnurgz5k6dwj5tk4fr2emh6uvumaa2ez6rx72u7wror26jzoz4qka"
    },
    "pieceSize": 34359738368,
    "termMin": 520000,
    "termMax": 779200,
    "expiration": 4141464,
    "height": 4127067
  },
  {
    "id": 69879010,
    "clientId": 2661434,
    "providerId": 3079766,
    "pieceCid": {
      "/": "baga6ea4seaqb7wzgou7zaxckxyg7fu7k3xrz6bfppkssikr6hqvyqlwix3rnmha"
    },
    "pieceSize": 34359738368,
    "termMin": 520000,
    "termMax": 779200,
    "expiration": 4141448,
    "height": 4127067
  },
  {
    "id": 69879034,
    "clientId": 2661434,
    "providerId": 3079766,
    "pieceCid": {
      "/": "baga6ea4seaqgqxhgpc2iadc3wh42klk54yhbui63ida2w7sckpkhman7wgqpidq"
    },
    "pieceSize": 34359738368,
    "termMin": 520000,
    "termMax": 779200,
    "expiration": 4141451,
    "height": 4127068
  },
  {
    "id": 69879033,
    "clientId": 2661434,
    "providerId": 3079766,
    "pieceCid": {
      "/": "baga6ea4seaqbefmlvqqo6nkb2nou2wadvqweufcde443rpeig5vz355fb2sq2by"
    },
    "pieceSize": 34359738368,
    "termMin": 520000,
    "termMax": 779200,
    "expiration": 4141450,
    "height": 4127068
  },
  {
    "id": 69879032,
    "clientId": 2661434,
    "providerId": 3079766,
    "pieceCid": {
      "/": "baga6ea4seaqbff7cbkieo4ju3dkp7z33t3kndnhbwuvwshokg6dei4ni4x46cna"
    },
    "pieceSize": 34359738368,
    "termMin": 520000,
    "termMax": 779200,
    "expiration": 4141450,
    "height": 4127068
  },
  {
    "id": 69879031,
    "clientId": 2661434,
    "providerId": 3079766,
    "pieceCid": {
      "/": "baga6ea4seaqjfualmynyieo3ptaf4gmdhfwh6isk6kylfould7vpvpfdqgjhini"
    },
    "pieceSize": 34359738368,
    "termMin": 520000,
    "termMax": 779200,
    "expiration": 4141451,
    "height": 4127068
  },
  {
    "id": 69879030,
    "clientId": 2661434,
    "providerId": 3079766,
    "pieceCid": {
      "/": "baga6ea4seaqb77pz7oyzjq76oesclfprkkucpjgapdrfgc3zrpr3a2m2bksdcba"
    },
    "pieceSize": 34359738368,
    "termMin": 520000,
    "termMax": 779200,
    "expiration": 4141451,
    "height": 4127068
  },
  {
    "id": 69879029,
    "clientId": 2661434,
    "providerId": 3079766,
    "pieceCid": {
      "/": "baga6ea4seaqhw2eo5y4jo3yphicaudc233zvl4p3lvycpxkoyesjn7t473566gq"
    },
    "pieceSize": 34359738368,
    "termMin": 520000,
    "termMax": 779200,
    "expiration": 4141451,
    "height": 4127068
  },
  {
    "id": 69879028,
    "clientId": 2661434,
    "providerId": 3079766,
    "pieceCid": {
      "/": "baga6ea4seaqbezhwbfaysq7wsexueinarzi5x7cl5uzjbq5z2yhgp2ijmpcjolq"
    },
    "pieceSize": 34359738368,
    "termMin": 520000,
    "termMax": 779200,
    "expiration": 4141450,
    "height": 4127068
  },
  {
    "id": 69879027,
    "clientId": 2661434,
    "providerId": 3079766,
    "pieceCid": {
      "/": "baga6ea4seaqmlpvfz5i3y3wfuz7s46uu6xe3x5iapxvlnby3pz63addtghpnmoa"
    },
    "pieceSize": 34359738368,
    "termMin": 520000,
    "termMax": 779200,
    "expiration": 4141466,
    "height": 4127068
  },
  {
    "id": 69879392,
    "clientId": 2661434,
    "providerId": 3079766,
    "pieceCid": {
      "/": "baga6ea4seaqggq4zibnkha3wv62icd34needomsi2ee4blyjlxpwn5yoldydmpi"
    },
    "pieceSize": 34359738368,
    "termMin": 520000,
    "termMax": 779200,
    "expiration": 4141466,
    "height": 4127079
  },
  {
    "id": 69879391,
    "clientId": 2661434,
    "providerId": 3079766,
    "pieceCid": {
      "/": "baga6ea4seaqo23peje7cgbwq4l6ufdjwjyaidhlzmuppixrwmoivrc75vq2iqjy"
    },
    "pieceSize": 34359738368,
    "termMin": 520000,
    "termMax": 779200,
    "expiration": 4141467,
    "height": 4127079
  },
  {
    "id": 69879390,
    "clientId": 2661434,
    "providerId": 3079766,
    "pieceCid": {
      "/": "baga6ea4seaqjc3rsbsfgupoahqhw32p23gylrghwhg27lo4flt5xrovsyquywkq"
    },
    "pieceSize": 34359738368,
    "termMin": 520000,
    "termMax": 779200,
    "expiration": 4141467,
    "height": 4127079
  },
  {
    "id": 69879389,
    "clientId": 2661434,
    "providerId": 3079766,
    "pieceCid": {
      "/": "baga6ea4seaqdg2fq2vjwtuxhi27wfgj7syzdj2gfzngztdkowolbvns7bwl2cja"
    },
    "pieceSize": 34359738368,
    "termMin": 520000,
    "termMax": 779200,
    "expiration": 4141467,
    "height": 4127079
  },
  {
    "id": 69879388,
    "clientId": 2661434,
    "providerId": 3079766,
    "pieceCid": {
      "/": "baga6ea4seaqd5r33touipcd2t3t66dq4del7fdzd3h44dvdvhhkp5a4j5bg34iq"
    },
    "pieceSize": 34359738368,
    "termMin": 520000,
    "termMax": 779200,
    "expiration": 4141467,
    "height": 4127079
  },
  {
    "id": 69879387,
    "clientId": 2661434,
    "providerId": 3079766,
    "pieceCid": {
      "/": "baga6ea4seaqiieybqjptsjkqy6qmlziqzrwnqmdao3zmtalc6up7xqb7lzm6wlq"
    },
    "pieceSize": 34359738368,
    "termMin": 520000,
    "termMax": 779200,
    "expiration": 4141466,
    "height": 4127079
  },
  {
    "id": 69879386,
    "clientId": 2661434,
    "providerId": 3079766,
    "pieceCid": {
      "/": "baga6ea4seaqodh4huv26vjajkwd5qamddpngx6cfwmgvlofig5lxcf3otub2cja"
    },
    "pieceSize": 34359738368,
    "termMin": 520000,
    "termMax": 779200,
    "expiration": 4141467,
    "height": 4127079
  },
  {
    "id": 69879385,
    "clientId": 2661434,
    "providerId": 3079766,
    "pieceCid": {
      "/": "baga6ea4seaqmiis2ymcucalpdhstc5kb4trdsn7q7mkxltwfc7u5zsxfzkl2obi"
    },
    "pieceSize": 34359738368,
    "termMin": 520000,
    "termMax": 779200,
    "expiration": 4141466,
    "height": 4127079
  },
  {
    "id": 69879607,
    "clientId": 2661434,
    "providerId": 3079766,
    "pieceCid": {
      "/": "baga6ea4seaqnj24spwmaxuml6jn2pi36za63c3pvpvl36ywyawx47tpjmhymkki"
    },
    "pieceSize": 34359738368,
    "termMin": 520000,
    "termMax": 779200,
    "expiration": 4141478,
    "height": 4127085
  },
  {
    "id": 69879606,
    "clientId": 2661434,
    "providerId": 3079766,
    "pieceCid": {
      "/": "baga6ea4seaqm6nmqe5yjeaurgjemif37ebhb3cisn6bcw6ajttgbpostlrnjeia"
    },
    "pieceSize": 34359738368,
    "termMin": 520000,
    "termMax": 779200,
    "expiration": 4141478,
    "height": 4127085
  },
  {
    "id": 69879605,
    "clientId": 2661434,
    "providerId": 3079766,
    "pieceCid": {
      "/": "baga6ea4seaqblx2aqoulslfr5d5v3pm4rs2mxzalzg3a7ytuppkuwrcog3ysuhi"
    },
    "pieceSize": 34359738368,
    "termMin": 520000,
    "termMax": 779200,
    "expiration": 4141477,
    "height": 4127085
  },
  {
    "id": 69879604,
    "clientId": 2661434,
    "providerId": 3079766,
    "pieceCid": {
      "/": "baga6ea4seaqatywzgizdyutu7zelclztm5ljgl5nl7aixchpp56bgvzdctwikoi"
    },
    "pieceSize": 34359738368,
    "termMin": 520000,
    "termMax": 779200,
    "expiration": 4141477,
    "height": 4127085
  },
  {
    "id": 69879603,
    "clientId": 2661434,
    "providerId": 3079766,
    "pieceCid": {
      "/": "baga6ea4seaqfl4epyuhdi4tffjhcrp6cwy2rmavigezrqamrd3pg2r4epzavgiq"
    },
    "pieceSize": 34359738368,
    "termMin": 520000,
    "termMax": 779200,
    "expiration": 4141478,
    "height": 4127085
  },
  {
    "id": 69879602,
    "clientId": 2661434,
    "providerId": 3079766,
    "pieceCid": {
      "/": "baga6ea4seaqb4prkpsgrqnmrry5k6lvsvjmxpi4r44jur3cwih3lxhedqhl72aa"
    },
    "pieceSize": 34359738368,
    "termMin": 520000,
    "termMax": 779200,
    "expiration": 4141477,
    "height": 4127085
  },
  {
    "id": 69879601,
    "clientId": 2661434,
    "providerId": 3079766,
    "pieceCid": {
      "/": "baga6ea4seaqk7q2lzvta5gd6ahln5wzzws43h4pql2mkuu3th3raraanehtiihi"
    },
    "pieceSize": 34359738368,
    "termMin": 520000,
    "termMax": 779200,
    "expiration": 4141477,
    "height": 4127085
  },
  {
    "id": 69879600,
    "clientId": 2661434,
    "providerId": 3079766,
    "pieceCid": {
      "/": "baga6ea4seaqe6hj46ewvb35t34weoywid2gsn2tt2hor3qlfh5dmanuixoa2wbi"
    },
    "pieceSize": 34359738368,
    "termMin": 520000,
    "termMax": 779200,
    "expiration": 4141479,
    "height": 4127085
  },
  {
    "id": 69879767,
    "clientId": 2661434,
    "providerId": 3079766,
    "pieceCid": {
      "/": "baga6ea4seaqfpndl67c3bdhtaqktxporme3hkedmpirisjzp7u3cmohuyau4mai"
    },
    "pieceSize": 34359738368,
    "termMin": 520000,
    "termMax": 779200,
    "expiration": 4141476,
    "height": 4127090
  },
  {
    "id": 69879766,
    "clientId": 2661434,
    "providerId": 3079766,
    "pieceCid": {
      "/": "baga6ea4seaqm22uvyd3sqqzmevzybiftcwr2c5uibisinifn6czq5bzvnsqocpi"
    },
    "pieceSize": 34359738368,
    "termMin": 520000,
    "termMax": 779200,
    "expiration": 4141478,
    "height": 4127090
  },
  {
    "id": 69879765,
    "clientId": 2661434,
    "providerId": 3079766,
    "pieceCid": {
      "/": "baga6ea4seaqatm2mrb5lhzlgl5u6lwmtxmggmlf6ntcia3k5r3ppvfnwbkmz4pq"
    },
    "pieceSize": 34359738368,
    "termMin": 520000,
    "termMax": 779200,
    "expiration": 4141479,
    "height": 4127090
  },
  {
    "id": 69879764,
    "clientId": 2661434,
    "providerId": 3079766,
    "pieceCid": {
      "/": "baga6ea4seaqn5fewgosudc2jew5clyezdtb3bszbxwrnajzykrsvaqzsys3kkay"
    },
    "pieceSize": 34359738368,
    "termMin": 520000,
    "termMax": 779200,
    "expiration": 4141479,
    "height": 4127090
  },
  {
    "id": 69879763,
    "clientId": 2661434,
    "providerId": 3079766,
    "pieceCid": {
      "/": "baga6ea4seaqktvkn2rewhjsh6kcefewzzurtpxwzfcvu345knlpuhre7jysakba"
    },
    "pieceSize": 34359738368,
    "termMin": 520000,
    "termMax": 779200,
    "expiration": 4141477,
    "height": 4127090
  },
  {
    "id": 69879762,
    "clientId": 2661434,
    "providerId": 3079766,
    "pieceCid": {
      "/": "baga6ea4seaqcirv7e3gk3q5msnip6b6k4xpc5o4b4doqac4a3chatpaydnnb6oi"
    },
    "pieceSize": 34359738368,
    "termMin": 520000,
    "termMax": 779200,
    "expiration": 4141478,
    "height": 4127090
  },
  {
    "id": 69879761,
    "clientId": 2661434,
    "providerId": 3079766,
    "pieceCid": {
      "/": "baga6ea4seaqamcz4xaza3cl7pfxwext2jlyfainhvbqfrjj46gn3dviiv2juwnq"
    },
    "pieceSize": 34359738368,
    "termMin": 520000,
    "termMax": 779200,
    "expiration": 4141479,
    "height": 4127090
  },
  {
    "id": 69879760,
    "clientId": 2661434,
    "providerId": 3079766,
    "pieceCid": {
      "/": "baga6ea4seaqclmb555qx74eywn3y5cqj3sutnwbppxexpb3evm5wt3intzrrmmq"
    },
    "pieceSize": 34359738368,
    "termMin": 520000,
    "termMax": 779200,
    "expiration": 4141478,
    "height": 4127090
  },
  {
    "id": 69880130,
    "clientId": 2661434,
    "providerId": 3079766,
    "pieceCid": {
      "/": "baga6ea4seaqhnihcry7ouj5w2ekhmqftanbqdaxxdgvtwsyalbomtkzlnf6igly"
    },
    "pieceSize": 34359738368,
    "termMin": 520000,
    "termMax": 779200,
    "expiration": 4141489,
    "height": 4127097
  },
  {
    "id": 69880129,
    "clientId": 2661434,
    "providerId": 3079766,
    "pieceCid": {
      "/": "baga6ea4seaqdimcvabazevmrte3xotkgqp5yoeuqqus7cuymsnucad4crwebagi"
    },
    "pieceSize": 34359738368,
    "termMin": 520000,
    "termMax": 779200,
    "expiration": 4141490,
    "height": 4127097
  },
  {
    "id": 69880128,
    "clientId": 2661434,
    "providerId": 3079766,
    "pieceCid": {
      "/": "baga6ea4seaqemmov5we3b2cr3l4xv46cwsaksdxfuhsjogwfu2rqxgln7v26gjq"
    },
    "pieceSize": 34359738368,
    "termMin": 520000,
    "termMax": 779200,
    "expiration": 4141489,
    "height": 4127097
  },
  {
    "id": 69880127,
    "clientId": 2661434,
    "providerId": 3079766,
    "pieceCid": {
      "/": "baga6ea4seaqnfu466ziiljsdo3p3xdi2rjofntqzt3uthmjmqton5trdxcflqki"
    },
    "pieceSize": 34359738368,
    "termMin": 520000,
    "termMax": 779200,
    "expiration": 4141490,
    "height": 4127097
  },
  {
    "id": 69880126,
    "clientId": 2661434,
    "providerId": 3079766,
    "pieceCid": {
      "/": "baga6ea4seaqftro6bfa4aflpstcrco4ywnhb6zg6v2n37mjphytfhilgb5amibi"
    },
    "pieceSize": 34359738368,
    "termMin": 520000,
    "termMax": 779200,
    "expiration": 4141489,
    "height": 4127097
  },
  {
    "id": 69880125,
    "clientId": 2661434,
    "providerId": 3079766,
    "pieceCid": {
      "/": "baga6ea4seaqpikuz6g2w32k773r2g5vynfpp7ht2rldjqc3navb7m7k27cltcjy"
    },
    "pieceSize": 34359738368,
    "termMin": 520000,
    "termMax": 779200,
    "expiration": 4141489,
    "height": 4127097
  },
  {
    "id": 69880124,
    "clientId": 2661434,
    "providerId": 3079766,
    "pieceCid": {
      "/": "baga6ea4seaqpqdaptrme6sk7fdg3s2bx2mwby7byj3s7amhonhsgeearml2l6jq"
    },
    "pieceSize": 34359738368,
    "termMin": 520000,
    "termMax": 779200,
    "expiration": 4141489,
    "height": 4127097
  },
  {
    "id": 69880123,
    "clientId": 2661434,
    "providerId": 3079766,
    "pieceCid": {
      "/": "baga6ea4seaqlwxs3hufekiloagg4f2dvjdymf6wsxxpvsi2l5wfychl7cpkw4aa"
    },
    "pieceSize": 34359738368,
    "termMin": 520000,
    "termMax": 779200,
    "expiration": 4141490,
    "height": 4127097
  },
  {
    "id": 69880562,
    "clientId": 2661434,
    "providerId": 3079766,
    "pieceCid": {
      "/": "baga6ea4seaqndhzsjatxh4ezdwu4sudgcejej5rcun5ef3c4ov2d26degbuucgi"
    },
    "pieceSize": 34359738368,
    "termMin": 520000,
    "termMax": 779200,
    "expiration": 4141506,
    "height": 4127107
  },
  {
    "id": 69880561,
    "clientId": 2661434,
    "providerId": 3079766,
    "pieceCid": {
      "/": "baga6ea4seaqeiqk7cqnwokxhszlcrekv2dhbzpmmdgd6b3m442la6vjr2cllaka"
    },
    "pieceSize": 34359738368,
    "termMin": 520000,
    "termMax": 779200,
    "expiration": 4141505,
    "height": 4127107
  },
  {
    "id": 69880560,
    "clientId": 2661434,
    "providerId": 3079766,
    "pieceCid": {
      "/": "baga6ea4seaqgn6h7nglzz4r4cndjvjvmat5fmayvw2gkikskhdu7p7wkua4tcdi"
    },
    "pieceSize": 34359738368,
    "termMin": 520000,
    "termMax": 779200,
    "expiration": 4141505,
    "height": 4127107
  },
  {
    "id": 69880559,
    "clientId": 2661434,
    "providerId": 3079766,
    "pieceCid": {
      "/": "baga6ea4seaqhc4wsydbvrmqrg5gsmdstsd7wtryvesvbeldxvqzps4qwrz3lapy"
    },
    "pieceSize": 34359738368,
    "termMin": 520000,
    "termMax": 779200,
    "expiration": 4141505,
    "height": 4127107
  },
  {
    "id": 69880558,
    "clientId": 2661434,
    "providerId": 3079766,
    "pieceCid": {
      "/": "baga6ea4seaqprvcb6gzwhhkpdquu73jhwngcz5ltszhtbtq2sjz3h2topofb2iq"
    },
    "pieceSize": 34359738368,
    "termMin": 520000,
    "termMax": 779200,
    "expiration": 4141505,
    "height": 4127107
  },
  {
    "id": 69880557,
    "clientId": 2661434,
    "providerId": 3079766,
    "pieceCid": {
      "/": "baga6ea4seaqawlqy2tamezd6wc5lvhxwdx5mnui526kafautmr7lzx762ke6kai"
    },
    "pieceSize": 34359738368,
    "termMin": 520000,
    "termMax": 779200,
    "expiration": 4141505,
    "height": 4127107
  },
  {
    "id": 69880556,
    "clientId": 2661434,
    "providerId": 3079766,
    "pieceCid": {
      "/": "baga6ea4seaqa4qgyllvf25h6b2dbotdkdvx2eu276wb26sllo6gyj7mkmuzo6ey"
    },
    "pieceSize": 34359738368,
    "termMin": 520000,
    "termMax": 779200,
    "expiration": 4141505,
    "height": 4127107
  },
  {
    "id": 69880555,
    "clientId": 2661434,
    "providerId": 3079766,
    "pieceCid": {
      "/": "baga6ea4seaqngv55q6mbtadqb72erogcqiyljbiftuo6vkg2zoxnuwrdfjdaigy"
    },
    "pieceSize": 34359738368,
    "termMin": 520000,
    "termMax": 779200,
    "expiration": 4141488,
    "height": 4127107
  },
  {
    "id": 69880620,
    "clientId": 2661434,
    "providerId": 3079766,
    "pieceCid": {
      "/": "baga6ea4seaqfujjkljkmq6zmmctxtxu7iidvr7kb5dvv7khrbb2m4wc5qyidugy"
    },
    "pieceSize": 34359738368,
    "termMin": 520000,
    "termMax": 779200,
    "expiration": 4141491,
    "height": 4127109
  },
  {
    "id": 69880619,
    "clientId": 2661434,
    "providerId": 3079766,
    "pieceCid": {
      "/": "baga6ea4seaqpv52m3sdjnghvxkf6cwizz2phbk4e323w4n53ue7xy5xd7lgzsla"
    },
    "pieceSize": 34359738368,
    "termMin": 520000,
    "termMax": 779200,
    "expiration": 4141491,
    "height": 4127109
  },
  {
    "id": 69880618,
    "clientId": 2661434,
    "providerId": 3079766,
    "pieceCid": {
      "/": "baga6ea4seaqggwzwmuc56bfozpwltxomu2wwh5cxuf6xsif7xw2isexunr7ympi"
    },
    "pieceSize": 34359738368,
    "termMin": 520000,
    "termMax": 779200,
    "expiration": 4141490,
    "height": 4127109
  },
  {
    "id": 69880617,
    "clientId": 2661434,
    "providerId": 3079766,
    "pieceCid": {
      "/": "baga6ea4seaqeonauzt6e2hzxp25bjompexxuyqoy2plao3jzdf7b6u6lcebreli"
    },
    "pieceSize": 34359738368,
    "termMin": 520000,
    "termMax": 779200,
    "expiration": 4141490,
    "height": 4127109
  },
  {
    "id": 69880616,
    "clientId": 2661434,
    "providerId": 3079766,
    "pieceCid": {
      "/": "baga6ea4seaqfard4dgv27m5uo7dkz2vtumzcdjl5maxjyjmrqjpzvkyotkuiuja"
    },
    "pieceSize": 34359738368,
    "termMin": 520000,
    "termMax": 779200,
    "expiration": 4141490,
    "height": 4127109
  },
  {
    "id": 69880615,
    "clientId": 2661434,
    "providerId": 3079766,
    "pieceCid": {
      "/": "baga6ea4seaqm23dbygdouw6rsjq4wzwcpbdv2npu3soglz26ycnpiwujvp6cuoq"
    },
    "pieceSize": 34359738368,
    "termMin": 520000,
    "termMax": 779200,
    "expiration": 4141491,
    "height": 4127109
  },
  {
    "id": 69880614,
    "clientId": 2661434,
    "providerId": 3079766,
    "pieceCid": {
      "/": "baga6ea4seaqjkjsjoiokhezxxx73xqepqt3pxuj2rr32xuzajgzzjqbaxvh3qgy"
    },
    "pieceSize": 34359738368,
    "termMin": 520000,
    "termMax": 779200,
    "expiration": 4141491,
    "height": 4127109
  },
  {
    "id": 69880613,
    "clientId": 2661434,
    "providerId": 3079766,
    "pieceCid": {
      "/": "baga6ea4seaqpd3lfir3uvzhxtjdozaxnsa36ecgk75v6wxrmnpjsj63bsiyfwaq"
    },
    "pieceSize": 34359738368,
    "termMin": 520000,
    "termMax": 779200,
    "expiration": 4141506,
    "height": 4127109
  },
  {
    "id": 69880985,
    "clientId": 2661434,
    "providerId": 3079766,
    "pieceCid": {
      "/": "baga6ea4seaqgd4f444vhgjdorhdtyz4ztfa7uzyombsebu5dwzisqyf5f7djmha"
    },
    "pieceSize": 34359738368,
    "termMin": 520000,
    "termMax": 779200,
    "expiration": 4141506,
    "height": 4127119
  },
  {
    "id": 69880984,
    "clientId": 2661434,
    "providerId": 3079766,
    "pieceCid": {
      "/": "baga6ea4seaqm3as7h3lbmom62ps3ysz6bojdkyifbwkp4cikapo2bdpacjkrcha"
    },
    "pieceSize": 34359738368,
    "termMin": 520000,
    "termMax": 779200,
    "expiration": 4141506,
    "height": 4127119
  },
  {
    "id": 69880983,
    "clientId": 2661434,
    "providerId": 3079766,
    "pieceCid": {
      "/": "baga6ea4seaqmlsiye65uhj5wwuuzkn4csfhceck62fjcl343dza2poeq2zu2yiy"
    },
    "pieceSize": 34359738368,
    "termMin": 520000,
    "termMax": 779200,
    "expiration": 4141507,
    "height": 4127119
  },
  {
    "id": 69880982,
    "clientId": 2661434,
    "providerId": 3079766,
    "pieceCid": {
      "/": "baga6ea4seaqchfgg56ub3gz74cgfqs7x4m7ihafcgsrnrhsnfnhqtlw3tu64qdy"
    },
    "pieceSize": 34359738368,
    "termMin": 520000,
    "termMax": 779200,
    "expiration": 4141507,
    "height": 4127119
  },
  {
    "id": 69880981,
    "clientId": 2661434,
    "providerId": 3079766,
    "pieceCid": {
      "/": "baga6ea4seaqp74ucbfb3col2v76hbpuvcajzo5dx3vpmcq3qhegzjbhzra65gei"
    },
    "pieceSize": 34359738368,
    "termMin": 520000,
    "termMax": 779200,
    "expiration": 4141506,
    "height": 4127119
  },
  {
    "id": 69880980,
    "clientId": 2661434,
    "providerId": 3079766,
    "pieceCid": {
      "/": "baga6ea4seaqnuhgkhrd2a3g4jsspifxclrne7rzndyxsvpubkb5ph3dvnkoe2lq"
    },
    "pieceSize": 34359738368,
    "termMin": 520000,
    "termMax": 779200,
    "expiration": 4141507,
    "height": 4127119
  },
  {
    "id": 69880979,
    "clientId": 2661434,
    "providerId": 3079766,
    "pieceCid": {
      "/": "baga6ea4seaqlfnabyuhsvsdzbbe3xqsbeyucq3ijxuh3m7llc2uvm2mr5ydx6lq"
    },
    "pieceSize": 34359738368,
    "termMin": 520000,
    "termMax": 779200,
    "expiration": 4141507,
    "height": 4127119
  },
  {
    "id": 69880978,
    "clientId": 2661434,
    "providerId": 3079766,
    "pieceCid": {
      "/": "baga6ea4seaqdwmkfhahsqhwntkctx7yutpuxbaewwnld4upgn47vodwiy4waobi"
    },
    "pieceSize": 34359738368,
    "termMin": 520000,
    "termMax": 779200,
    "expiration": 4141507,
    "height": 4127119
  },
  {
    "id": 69881927,
    "clientId": 2661434,
    "providerId": 3079766,
    "pieceCid": {
      "/": "baga6ea4seaqboxezrrc44kdmkc566a2p3oaagnkeutusr7wksrriu5zsyea24kq"
    },
    "pieceSize": 34359738368,
    "termMin": 520000,
    "termMax": 779200,
    "expiration": 4141524,
    "height": 4127141
  },
  {
    "id": 69881926,
    "clientId": 2661434,
    "providerId": 3079766,
    "pieceCid": {
      "/": "baga6ea4seaqfgdz4llmr5nd7p64aggtnqu3yf7ijz45fhwtns4sngihp7fc32bq"
    },
    "pieceSize": 34359738368,
    "termMin": 520000,
    "termMax": 779200,
    "expiration": 4141525,
    "height": 4127141
  },
  {
    "id": 69881925,
    "clientId": 2661434,
    "providerId": 3079766,
    "pieceCid": {
      "/": "baga6ea4seaqmvbwiixonsz7xkh5q7aicz7f3w4ci52wd7sclie7ugcjcdlnoyhq"
    },
    "pieceSize": 34359738368,
    "termMin": 520000,
    "termMax": 779200,
    "expiration": 4141521,
    "height": 4127141
  },
  {
    "id": 69881924,
    "clientId": 2661434,
    "providerId": 3079766,
    "pieceCid": {
      "/": "baga6ea4seaqiqksohimjgvaepw4tix7aobikhrn4374frn4ug22p7tunwomt2lq"
    },
    "pieceSize": 34359738368,
    "termMin": 520000,
    "termMax": 779200,
    "expiration": 4141522,
    "height": 4127141
  },
  {
    "id": 69881923,
    "clientId": 2661434,
    "providerId": 3079766,
    "pieceCid": {
      "/": "baga6ea4seaqnghcjc6qo53t5twgco6ncsqsghmvwwqaxtg3swr3mimvupcwlmaq"
    },
    "pieceSize": 34359738368,
    "termMin": 520000,
    "termMax": 779200,
    "expiration": 4141527,
    "height": 4127141
  },
  {
    "id": 69881922,
    "clientId": 2661434,
    "providerId": 3079766,
    "pieceCid": {
      "/": "baga6ea4seaqmyc5rqklvzpzhbi5ddfrv6z6tyovayorjv6e674v2g7cy7w324pi"
    },
    "pieceSize": 34359738368,
    "termMin": 520000,
    "termMax": 779200,
    "expiration": 4141524,
    "height": 4127141
  },
  {
    "id": 69881921,
    "clientId": 2661434,
    "providerId": 3079766,
    "pieceCid": {
      "/": "baga6ea4seaqhamv5avzu2ta5ep6cgnlcw5sh7ey6hmch7sz6fhnconrqzvlkcmq"
    },
    "pieceSize": 34359738368,
    "termMin": 520000,
    "termMax": 779200,
    "expiration": 4141522,
    "height": 4127141
  },
  {
    "id": 69881920,
    "clientId": 2661434,
    "providerId": 3079766,
    "pieceCid": {
      "/": "baga6ea4seaqlqxbowpif5ib6hzzgidgcvvfnzhll6f2ilvyp6b2lvtoewdwrkeq"
    },
    "pieceSize": 34359738368,
    "termMin": 520000,
    "termMax": 779200,
    "expiration": 4141522,
    "height": 4127141
  },
  {
    "id": 69881917,
    "clientId": 2661434,
    "providerId": 3079766,
    "pieceCid": {
      "/": "baga6ea4seaqfk2twk5pti74y6nsylz7yrkxnkb5jeuppnvdqml2mfpdornfkegy"
    },
    "pieceSize": 34359738368,
    "termMin": 520000,
    "termMax": 779200,
    "expiration": 4141521,
    "height": 4127141
  },
  {
    "id": 69881916,
    "clientId": 2661434,
    "providerId": 3079766,
    "pieceCid": {
      "/": "baga6ea4seaqdkt5763q4cvfctja5klcczcavau6lmlblzznzwm7frsvpuxgfcba"
    },
    "pieceSize": 34359738368,
    "termMin": 520000,
    "termMax": 779200,
    "expiration": 4141523,
    "height": 4127141
  },
  {
    "id": 69881915,
    "clientId": 2661434,
    "providerId": 3079766,
    "pieceCid": {
      "/": "baga6ea4seaqgw2tjizrmivke7mfgwhkc5wn7ufyqi6mxpo4llxqyux2giwngwci"
    },
    "pieceSize": 34359738368,
    "termMin": 520000,
    "termMax": 779200,
    "expiration": 4141524,
    "height": 4127141
  },
  {
    "id": 69881914,
    "clientId": 2661434,
    "providerId": 3079766,
    "pieceCid": {
      "/": "baga6ea4seaqidguzr7zwq7mh2fle6zmjbatggqcii3ly5og5u5otwv3q3mgbgaq"
    },
    "pieceSize": 34359738368,
    "termMin": 520000,
    "termMax": 779200,
    "expiration": 4141523,
    "height": 4127141
  },
  {
    "id": 69881913,
    "clientId": 2661434,
    "providerId": 3079766,
    "pieceCid": {
      "/": "baga6ea4seaqi7klx5xqk6jtxs4x2qidfaus63q3z5xqd45htn5jzhqezlzedsmq"
    },
    "pieceSize": 34359738368,
    "termMin": 520000,
    "termMax": 779200,
    "expiration": 4141525,
    "height": 4127141
  },
  {
    "id": 69881912,
    "clientId": 2661434,
    "providerId": 3079766,
    "pieceCid": {
      "/": "baga6ea4seaqe35wu4oeiyfluk3izvshrkc7e2cfmatyzs3oo2ln4hz5ofbdl6eq"
    },
    "pieceSize": 34359738368,
    "termMin": 520000,
    "termMax": 779200,
    "expiration": 4141526,
    "height": 4127141
  },
  {
    "id": 69881911,
    "clientId": 2661434,
    "providerId": 3079766,
    "pieceCid": {
      "/": "baga6ea4seaqlseckk7exafl75mdlql57db3eiv56gkvvgemfntdfarg32fqqeki"
    },
    "pieceSize": 34359738368,
    "termMin": 520000,
    "termMax": 779200,
    "expiration": 4141526,
    "height": 4127141
  },
  {
    "id": 69881910,
    "clientId": 2661434,
    "providerId": 3079766,
    "pieceCid": {
      "/": "baga6ea4seaqiyxadc7mmv6qszeagz5imuiowvwvvjb4fuch6boqxqi7ka7j2cfi"
    },
    "pieceSize": 34359738368,
    "termMin": 520000,
    "termMax": 779200,
    "expiration": 4141526,
    "height": 4127141
  },
  {
    "id": 69881909,
    "clientId": 2661434,
    "providerId": 3079766,
    "pieceCid": {
      "/": "baga6ea4seaqj5eprxqjjmbyriidxcpu6veac62xfb7t2hyaoil3joonrhbi4wbi"
    },
    "pieceSize": 34359738368,
    "termMin": 520000,
    "termMax": 779200,
    "expiration": 4141525,
    "height": 4127141
  },
  {
    "id": 69881908,
    "clientId": 2661434,
    "providerId": 3079766,
    "pieceCid": {
      "/": "baga6ea4seaqjvpgvle3xmhygwz2avrr6xqltgt3rgxnpa6fkua4xozfwknkhkea"
    },
    "pieceSize": 34359738368,
    "termMin": 520000,
    "termMax": 779200,
    "expiration": 4141527,
    "height": 4127141
  },
  {
    "id": 69881907,
    "clientId": 2661434,
    "providerId": 3079766,
    "pieceCid": {
      "/": "baga6ea4seaqktuyxqwdppdagj6xd5x3vqg4xkewv4ktygn5hqdietrpios7miny"
    },
    "pieceSize": 34359738368,
    "termMin": 520000,
    "termMax": 779200,
    "expiration": 4141523,
    "height": 4127141
  },
  {
    "id": 69881906,
    "clientId": 2661434,
    "providerId": 3079766,
    "pieceCid": {
      "/": "baga6ea4seaqj2z5bw7zv64tla7vdvqc4tw6olkcdlg7aufoirt2qod6fzyrxwpi"
    },
    "pieceSize": 34359738368,
    "termMin": 520000,
    "termMax": 779200,
    "expiration": 4141525,
    "height": 4127141
  },
  {
    "id": 69881905,
    "clientId": 2661434,
    "providerId": 3079766,
    "pieceCid": {
      "/": "baga6ea4seaqkkvwuaglovhcuyz3vi4rh7jg3ge5d2zjpw5t3q7vb7xwzyr55kay"
    },
    "pieceSize": 34359738368,
    "termMin": 520000,
    "termMax": 779200,
    "expiration": 4141527,
    "height": 4127141
  },
  {
    "id": 69881904,
    "clientId": 2661434,
    "providerId": 3079766,
    "pieceCid": {
      "/": "baga6ea4seaqlaq4r2u4rjr26tic6ndz4ikfsemvon5vxoi3ckzuzobobesvzsjy"
    },
    "pieceSize": 34359738368,
    "termMin": 520000,
    "termMax": 779200,
    "expiration": 4141526,
    "height": 4127141
  },
  {
    "id": 69881903,
    "clientId": 2661434,
    "providerId": 3079766,
    "pieceCid": {
      "/": "baga6ea4seaqo44zdvredacu6uxesbcnm24zmqa44uehgymtw63cpxov67dvi2fy"
    },
    "pieceSize": 34359738368,
    "termMin": 520000,
    "termMax": 779200,
    "expiration": 4141525,
    "height": 4127141
  },
  {
    "id": 69881902,
    "clientId": 2661434,
    "providerId": 3079766,
    "pieceCid": {
      "/": "baga6ea4seaqjyabeliahel2cffyc2fpilxzbwzg4ljz7wyjvthysicsqvsfqama"
    },
    "pieceSize": 34359738368,
    "termMin": 520000,
    "termMax": 779200,
    "expiration": 4141521,
    "height": 4127141
  },
  {
    "id": 69881901,
    "clientId": 2661434,
    "providerId": 3079766,
    "pieceCid": {
      "/": "baga6ea4seaqaqlegwmcc5k6xkvwdjkguc33w6fprb7lanmsjszpikfbrxhnlaji"
    },
    "pieceSize": 34359738368,
    "termMin": 520000,
    "termMax": 779200,
    "expiration": 4141522,
    "height": 4127141
  },
  {
    "id": 69881900,
    "clientId": 2661434,
    "providerId": 3079766,
    "pieceCid": {
      "/": "baga6ea4seaqglfgsw45twgwqrhvwnq663y66zlrs2q3wc5maruaymyahw5mqwdq"
    },
    "pieceSize": 34359738368,
    "termMin": 520000,
    "termMax": 779200,
    "expiration": 4141522,
    "height": 4127141
  },
  {
    "id": 69881899,
    "clientId": 2661434,
    "providerId": 3079766,
    "pieceCid": {
      "/": "baga6ea4seaqoa5djtkokiv6fgs72vlfmgmruqbk267m2lj5vudqou3e3tzv52ai"
    },
    "pieceSize": 34359738368,
    "termMin": 520000,
    "termMax": 779200,
    "expiration": 4141523,
    "height": 4127141
  },
  {
    "id": 69881898,
    "clientId": 2661434,
    "providerId": 3079766,
    "pieceCid": {
      "/": "baga6ea4seaqpzd7l3lc2zx6dx7wjw2bhdkrtkd7zjvxd4j3cpgn7caivmfdwgia"
    },
    "pieceSize": 34359738368,
    "termMin": 520000,
    "termMax": 779200,
    "expiration": 4141526,
    "height": 4127141
  },
  {
    "id": 69881897,
    "clientId": 2661434,
    "providerId": 3079766,
    "pieceCid": {
      "/": "baga6ea4seaqjo73emnhfdxkpbb42iqyiokyrr2p6grmeg4tg7jfped26wcdx4nq"
    },
    "pieceSize": 34359738368,
    "termMin": 520000,
    "termMax": 779200,
    "expiration": 4141521,
    "height": 4127141
  },
  {
    "id": 69881896,
    "clientId": 2661434,
    "providerId": 3079766,
    "pieceCid": {
      "/": "baga6ea4seaqf4v3jvuu5c2brzrxur7gng6zwieufrxuebiiras4dfwwurndn2dy"
    },
    "pieceSize": 34359738368,
    "termMin": 520000,
    "termMax": 779200,
    "expiration": 4141521,
    "height": 4127141
  },
  {
    "id": 69881895,
    "clientId": 2661434,
    "providerId": 3079766,
    "pieceCid": {
      "/": "baga6ea4seaqeajlbknh2gu2bv32vgolnir5jrjydml5rsd33o2poc74k272e4mi"
    },
    "pieceSize": 34359738368,
    "termMin": 520000,
    "termMax": 779200,
    "expiration": 4141523,
    "height": 4127141
  },
  {
    "id": 69881894,
    "clientId": 2661434,
    "providerId": 3079766,
    "pieceCid": {
      "/": "baga6ea4seaqeuiwv5dkuzqxge47oqahk7gxoln23oyw25p4titlpfqqkru66woq"
    },
    "pieceSize": 34359738368,
    "termMin": 520000,
    "termMax": 779200,
    "expiration": 4141527,
    "height": 4127141
  },
  {
    "id": 69882614,
    "clientId": 2661434,
    "providerId": 3079766,
    "pieceCid": {
      "/": "baga6ea4seaqpjwf4evgyire4elml2qptiej4gs262hgqg7vugwijnx7frcvtady"
    },
    "pieceSize": 34359738368,
    "termMin": 520000,
    "termMax": 779200,
    "expiration": 4141558,
    "height": 4127160
  },
  {
    "id": 69882613,
    "clientId": 2661434,
    "providerId": 3079766,
    "pieceCid": {
      "/": "baga6ea4seaqhhstlkvupsvnswwrdivv5if3kventtln5xnfedekp7yztx5dnkby"
    },
    "pieceSize": 34359738368,
    "termMin": 520000,
    "termMax": 779200,
    "expiration": 4141558,
    "height": 4127160
  },
  {
    "id": 69882612,
    "clientId": 2661434,
    "providerId": 3079766,
    "pieceCid": {
      "/": "baga6ea4seaqija7opdoojci34bki3mvvtgyq3jwctfoyvpzvk6o3csxqozximoy"
    },
    "pieceSize": 34359738368,
    "termMin": 520000,
    "termMax": 779200,
    "expiration": 4141558,
    "height": 4127160
  },
  {
    "id": 69882611,
    "clientId": 2661434,
    "providerId": 3079766,
    "pieceCid": {
      "/": "baga6ea4seaqgv6ssjpdyftv4uvbiwqynwul7dlyb445u7p5axgdkpgnojg5ccfi"
    },
    "pieceSize": 34359738368,
    "termMin": 520000,
    "termMax": 779200,
    "expiration": 4141558,
    "height": 4127160
  },
  {
    "id": 69882610,
    "clientId": 2661434,
    "providerId": 3079766,
    "pieceCid": {
      "/": "baga6ea4seaqgqiqhl6o6qkpd6dvsylaf3zszcykgtn53cjgkutmy7hl2zs6ympq"
    },
    "pieceSize": 34359738368,
    "termMin": 520000,
    "termMax": 779200,
    "expiration": 4141558,
    "height": 4127160
  },
  {
    "id": 69882609,
    "clientId": 2661434,
    "providerId": 3079766,
    "pieceCid": {
      "/": "baga6ea4seaqggxmujnglj4ocexpybkbjgbqxzii5zkkpdvyuroewhvnbtioecjy"
    },
    "pieceSize": 34359738368,
    "termMin": 520000,
    "termMax": 779200,
    "expiration": 4141558,
    "height": 4127160
  },
  {
    "id": 69882608,
    "clientId": 2661434,
    "providerId": 3079766,
    "pieceCid": {
      "/": "baga6ea4seaqan473luyt46v324332dprgmlsnlnbehuwi6dydsnf5tn2u4v46mq"
    },
    "pieceSize": 34359738368,
    "termMin": 520000,
    "termMax": 779200,
    "expiration": 4141557,
    "height": 4127160
  },
  {
    "id": 69882607,
    "clientId": 2661434,
    "providerId": 3079766,
    "pieceCid": {
      "/": "baga6ea4seaqdaxjcpdg43kp3i7z4hbow6eeutjczl2mkvmxzlohz5o3mqp2egnq"
    },
    "pieceSize": 34359738368,
    "termMin": 520000,
    "termMax": 779200,
    "expiration": 4141557,
    "height": 4127160
  }
]